{
    "file": "Bava Metzia_56b", 
    "words": [
        {
            "lang": 0, 
            "gold_pos": "", 
            "confidence": 1.2390747464804267e-11, 
            "word": "קדשים", 
            "gold_class": 0, 
            "predicted": "V01"
        }, 
        {
            "lang": 0, 
            "gold_pos": "", 
            "confidence": 2.8449084548254115e-14, 
            "word": "שהוא", 
            "gold_class": 0, 
            "predicted": "V01"
        }, 
        {
            "lang": 0, 
            "gold_pos": "", 
            "confidence": 0.00098523157092006517, 
            "word": "חייב", 
            "gold_class": 0, 
            "predicted": "V02"
        }, 
        {
            "lang": 0, 
            "gold_pos": "", 
            "confidence": 5.0107381876968219e-09, 
            "word": "באחריותן", 
            "gold_class": 0, 
            "predicted": "p02"
        }, 
        {
            "lang": 0, 
            "gold_pos": "", 
            "confidence": 4.4729446454833552e-15, 
            "word": "יש", 
            "gold_class": 0, 
            "predicted": "V01"
        }, 
        {
            "lang": 0, 
            "gold_pos": "", 
            "confidence": 4.4551297524656249e-16, 
            "word": "להן", 
            "gold_class": 0, 
            "predicted": "P"
        }, 
        {
            "lang": 0, 
            "gold_pos": "", 
            "confidence": 1.0106927918562318e-14, 
            "word": "אונאה", 
            "gold_class": 0, 
            "predicted": "V01"
        }, 
        {
            "lang": 0, 
            "gold_pos": "", 
            "confidence": 5.7144453013968935e-05, 
            "word": "ושאינו", 
            "gold_class": 0, 
            "predicted": "V01"
        }, 
        {
            "lang": 0, 
            "gold_pos": "", 
            "confidence": 7.7651528918454464e-05, 
            "word": "חייב", 
            "gold_class": 0, 
            "predicted": "A03"
        }, 
        {
            "lang": 0, 
            "gold_pos": "", 
            "confidence": 2.1947853770359031e-06, 
            "word": "באחריותן", 
            "gold_class": 0, 
            "predicted": "A02"
        }, 
        {
            "lang": 0, 
            "gold_pos": "", 
            "confidence": 3.0399155184828836e-08, 
            "word": "אין", 
            "gold_class": 0, 
            "predicted": "c"
        }, 
        {
            "lang": 0, 
            "gold_pos": "", 
            "confidence": 2.3889732968862915e-17, 
            "word": "להן", 
            "gold_class": 0, 
            "predicted": "P"
        }, 
        {
            "lang": 0, 
            "gold_pos": "", 
            "confidence": 3.3423253823992097e-13, 
            "word": "אונאה", 
            "gold_class": 0, 
            "predicted": "N02"
        }, 
        {
            "lang": 0, 
            "gold_pos": "", 
            "confidence": 0.0015614887862183257, 
            "word": "רבי", 
            "gold_class": 0, 
            "predicted": "A05"
        }, 
        {
            "lang": 0, 
            "gold_pos": "", 
            "confidence": 6.5981091397194611e-16, 
            "word": "יהודה", 
            "gold_class": 0, 
            "predicted": "V01"
        }, 
        {
            "lang": 0, 
            "gold_pos": "", 
            "confidence": 4.652199474745534e-08, 
            "word": "אומר", 
            "gold_class": 0, 
            "predicted": "PN"
        }, 
        {
            "lang": 0, 
            "gold_pos": "", 
            "confidence": 2.8043730972114692e-09, 
            "word": "אף", 
            "gold_class": 0, 
            "predicted": "a"
        }, 
        {
            "lang": 0, 
            "gold_pos": "", 
            "confidence": 7.3368687494068074e-08, 
            "word": "המוכר", 
            "gold_class": 0, 
            "predicted": "V04"
        }, 
        {
            "lang": 0, 
            "gold_pos": "", 
            "confidence": 2.7632724761463478e-06, 
            "word": "ספר", 
            "gold_class": 0, 
            "predicted": "V01"
        }, 
        {
            "lang": 0, 
            "gold_pos": "", 
            "confidence": 5.144254393531206e-11, 
            "word": "תורה", 
            "gold_class": 0, 
            "predicted": "N02"
        }, 
        {
            "lang": 0, 
            "gold_pos": "", 
            "confidence": 2.0650529814361841e-15, 
            "word": "בהמה", 
            "gold_class": 0, 
            "predicted": "p02"
        }, 
        {
            "lang": 0, 
            "gold_pos": "", 
            "confidence": 1.1817659682978439e-05, 
            "word": "ומרגלית", 
            "gold_class": 0, 
            "predicted": "GN"
        }, 
        {
            "lang": 0, 
            "gold_pos": "", 
            "confidence": 1.4373422267775425e-07, 
            "word": "אין", 
            "gold_class": 0, 
            "predicted": "V03"
        }, 
        {
            "lang": 0, 
            "gold_pos": "", 
            "confidence": 1.5841889372493052e-12, 
            "word": "להם", 
            "gold_class": 0, 
            "predicted": "p01"
        }, 
        {
            "lang": 0, 
            "gold_pos": "", 
            "confidence": 7.1423416771751152e-12, 
            "word": "אונאה", 
            "gold_class": 0, 
            "predicted": "V01"
        }, 
        {
            "lang": 0, 
            "gold_pos": "", 
            "confidence": 1.6497838051839515e-16, 
            "word": "אמרו", 
            "gold_class": 0, 
            "predicted": "V01"
        }, 
        {
            "lang": 0, 
            "gold_pos": "", 
            "confidence": 1.2177083319498179e-10, 
            "word": "לו", 
            "gold_class": 0, 
            "predicted": "a"
        }, 
        {
            "lang": 0, 
            "gold_pos": "", 
            "confidence": 5.1623051109355875e-17, 
            "word": "לא", 
            "gold_class": 0, 
            "predicted": "a"
        }, 
        {
            "lang": 0, 
            "gold_pos": "", 
            "confidence": 3.8379719282206769e-15, 
            "word": "אמרו", 
            "gold_class": 0, 
            "predicted": "V01"
        }, 
        {
            "lang": 0, 
            "gold_pos": "", 
            "confidence": 3.5058710498955318e-12, 
            "word": "אלא", 
            "gold_class": 0, 
            "predicted": "c"
        }, 
        {
            "lang": 0, 
            "gold_pos": "", 
            "confidence": 7.1868395036134173e-16, 
            "word": "את", 
            "gold_class": 0, 
            "predicted": "V01"
        }, 
        {
            "lang": 0, 
            "gold_pos": "", 
            "confidence": 3.2244286558792126e-11, 
            "word": "אלו", 
            "gold_class": 0, 
            "predicted": "a"
        }, 
        {
            "lang": 0, 
            "gold_pos": "", 
            "confidence": 3.215807154932753e-07, 
            "word": "גמ׳", 
            "gold_class": 0, 
            "predicted": "n01"
        }, 
        {
            "lang": 1, 
            "gold_pos": "", 
            "confidence": 1.4465055865424994e-09, 
            "word": "מנהני", 
            "gold_class": 0, 
            "predicted": "N05"
        }, 
        {
            "lang": 1, 
            "gold_pos": "N05", 
            "confidence": 0.0, 
            "word": "מילי", 
            "gold_class": 1, 
            "predicted": "N05"
        }, 
        {
            "lang": 1, 
            "gold_pos": "V01", 
            "confidence": 0.0, 
            "word": "דתנו", 
            "gold_class": 1, 
            "predicted": "V01"
        }, 
        {
            "lang": 1, 
            "gold_pos": "N05", 
            "confidence": 0.0, 
            "word": "רבנן", 
            "gold_class": 1, 
            "predicted": "N05"
        }, 
        {
            "lang": 0, 
            "gold_pos": "", 
            "confidence": 1.3178618434030818e-07, 
            "word": "וכי", 
            "gold_class": 0, 
            "predicted": "n01"
        }, 
        {
            "lang": 0, 
            "gold_pos": "", 
            "confidence": 1.2085406490095827e-05, 
            "word": "תמכרו", 
            "gold_class": 0, 
            "predicted": "N05"
        }, 
        {
            "lang": 0, 
            "gold_pos": "", 
            "confidence": 3.9235423108743029e-08, 
            "word": "ממכר", 
            "gold_class": 0, 
            "predicted": "PN"
        }, 
        {
            "lang": 0, 
            "gold_pos": "", 
            "confidence": 3.7265659839811138e-09, 
            "word": "לעמיתך", 
            "gold_class": 0, 
            "predicted": "N02"
        }, 
        {
            "lang": 0, 
            "gold_pos": "", 
            "confidence": 9.5120218049677469e-11, 
            "word": "או", 
            "gold_class": 0, 
            "predicted": "V01"
        }, 
        {
            "lang": 0, 
            "gold_pos": "", 
            "confidence": 2.1911594319907292e-16, 
            "word": "קנה", 
            "gold_class": 0, 
            "predicted": "V01"
        }, 
        {
            "lang": 0, 
            "gold_pos": "", 
            "confidence": 7.1142043008669277e-15, 
            "word": "מיד", 
            "gold_class": 0, 
            "predicted": "c"
        }, 
        {
            "lang": 0, 
            "gold_pos": "", 
            "confidence": 1.7574250730806009e-09, 
            "word": "עמיתך", 
            "gold_class": 0, 
            "predicted": "N02"
        }, 
        {
            "lang": 0, 
            "gold_pos": "", 
            "confidence": 7.9378112609383266e-12, 
            "word": "דבר", 
            "gold_class": 0, 
            "predicted": "N01"
        }, 
        {
            "lang": 0, 
            "gold_pos": "", 
            "confidence": 4.3470398808845907e-12, 
            "word": "הנקנה", 
            "gold_class": 0, 
            "predicted": "N01"
        }, 
        {
            "lang": 0, 
            "gold_pos": "", 
            "confidence": 1.053270384140925e-13, 
            "word": "מיד", 
            "gold_class": 0, 
            "predicted": "c"
        }, 
        {
            "lang": 0, 
            "gold_pos": "", 
            "confidence": 7.465388468576961e-12, 
            "word": "ליד", 
            "gold_class": 0, 
            "predicted": "V01"
        }, 
        {
            "lang": 0, 
            "gold_pos": "", 
            "confidence": 0.0001227194540305818, 
            "word": "יצאו", 
            "gold_class": 0, 
            "predicted": "A02"
        }, 
        {
            "lang": 0, 
            "gold_pos": "", 
            "confidence": 1.192433145436284e-07, 
            "word": "קרקעות", 
            "gold_class": 0, 
            "predicted": "V02"
        }, 
        {
            "lang": 0, 
            "gold_pos": "", 
            "confidence": 2.1287594761568752e-11, 
            "word": "שאינן", 
            "gold_class": 0, 
            "predicted": "V01"
        }, 
        {
            "lang": 0, 
            "gold_pos": "", 
            "confidence": 4.5619291449373508e-10, 
            "word": "מטלטלים", 
            "gold_class": 0, 
            "predicted": "V01"
        }, 
        {
            "lang": 0, 
            "gold_pos": "", 
            "confidence": 0.0016716750835670869, 
            "word": "יצאו", 
            "gold_class": 0, 
            "predicted": "A02"
        }, 
        {
            "lang": 0, 
            "gold_pos": "", 
            "confidence": 1.4470312494930454e-16, 
            "word": "עבדים", 
            "gold_class": 0, 
            "predicted": "V01"
        }, 
        {
            "lang": 0, 
            "gold_pos": "", 
            "confidence": 3.4719647468711388e-12, 
            "word": "שהוקשו", 
            "gold_class": 0, 
            "predicted": "V01"
        }, 
        {
            "lang": 0, 
            "gold_pos": "", 
            "confidence": 8.1150574197236267e-08, 
            "word": "לקרקעות", 
            "gold_class": 0, 
            "predicted": "N02"
        }, 
        {
            "lang": 0, 
            "gold_pos": "", 
            "confidence": 5.8497991210513259e-06, 
            "word": "יצאו", 
            "gold_class": 0, 
            "predicted": "A01"
        }, 
        {
            "lang": 0, 
            "gold_pos": "", 
            "confidence": 2.7894280013846648e-05, 
            "word": "שטרות", 
            "gold_class": 0, 
            "predicted": "V01"
        }, 
        {
            "lang": 0, 
            "gold_pos": "", 
            "confidence": 3.5461431383000311e-17, 
            "word": "דכתיב", 
            "gold_class": 0, 
            "predicted": "V01"
        }, 
        {
            "lang": 0, 
            "gold_pos": "", 
            "confidence": 3.007466175024474e-08, 
            "word": "וכי", 
            "gold_class": 0, 
            "predicted": "n01"
        }, 
        {
            "lang": 0, 
            "gold_pos": "", 
            "confidence": 0.00074764857898818244, 
            "word": "תמכרו", 
            "gold_class": 0, 
            "predicted": "N05"
        }, 
        {
            "lang": 0, 
            "gold_pos": "", 
            "confidence": 4.4416181931266577e-09, 
            "word": "ממכר", 
            "gold_class": 0, 
            "predicted": "PN"
        }, 
        {
            "lang": 0, 
            "gold_pos": "", 
            "confidence": 5.7575973698017288e-07, 
            "word": "שגופו", 
            "gold_class": 0, 
            "predicted": "V02"
        }, 
        {
            "lang": 0, 
            "gold_pos": "", 
            "confidence": 9.9628941875809276e-09, 
            "word": "מכור", 
            "gold_class": 0, 
            "predicted": "V03"
        }, 
        {
            "lang": 0, 
            "gold_pos": "", 
            "confidence": 3.1426722316279618e-09, 
            "word": "וגופו", 
            "gold_class": 0, 
            "predicted": "V03"
        }, 
        {
            "lang": 1, 
            "gold_pos": "", 
            "confidence": 6.0720005712251546e-15, 
            "word": "קנוי", 
            "gold_class": 0, 
            "predicted": "V01"
        }, 
        {
            "lang": 0, 
            "gold_pos": "", 
            "confidence": 2.1000764893971747e-07, 
            "word": "יצאו", 
            "gold_class": 0, 
            "predicted": "N02"
        }, 
        {
            "lang": 0, 
            "gold_pos": "", 
            "confidence": 1.0412503092006035e-10, 
            "word": "שטרות", 
            "gold_class": 0, 
            "predicted": "V01"
        }, 
        {
            "lang": 0, 
            "gold_pos": "", 
            "confidence": 4.2195918534172831e-07, 
            "word": "שאין", 
            "gold_class": 0, 
            "predicted": "N04"
        }, 
        {
            "lang": 0, 
            "gold_pos": "", 
            "confidence": 5.4579491565387425e-06, 
            "word": "גופן", 
            "gold_class": 0, 
            "predicted": "n01"
        }, 
        {
            "lang": 0, 
            "gold_pos": "", 
            "confidence": 4.9407132715505162e-10, 
            "word": "מכור", 
            "gold_class": 0, 
            "predicted": "V01"
        }, 
        {
            "lang": 0, 
            "gold_pos": "", 
            "confidence": 1.0459137555481481e-16, 
            "word": "ואין", 
            "gold_class": 0, 
            "predicted": "P"
        }, 
        {
            "lang": 0, 
            "gold_pos": "", 
            "confidence": 6.5278454663604882e-05, 
            "word": "גופן", 
            "gold_class": 0, 
            "predicted": "N05"
        }, 
        {
            "lang": 1, 
            "gold_pos": "", 
            "confidence": 1.3353618388499703e-14, 
            "word": "קנוי", 
            "gold_class": 0, 
            "predicted": "V01"
        }, 
        {
            "lang": 0, 
            "gold_pos": "", 
            "confidence": 2.9431924602186046e-13, 
            "word": "ואינן", 
            "gold_class": 0, 
            "predicted": "p02"
        }, 
        {
            "lang": 0, 
            "gold_pos": "", 
            "confidence": 4.3641589076778403e-05, 
            "word": "עומדין", 
            "gold_class": 0, 
            "predicted": "N02"
        }, 
        {
            "lang": 0, 
            "gold_pos": "", 
            "confidence": 2.3403032234197244e-09, 
            "word": "אלא", 
            "gold_class": 0, 
            "predicted": "c"
        }, 
        {
            "lang": 0, 
            "gold_pos": "", 
            "confidence": 6.3722164338521158e-12, 
            "word": "לראיה", 
            "gold_class": 0, 
            "predicted": "N02"
        }, 
        {
            "lang": 0, 
            "gold_pos": "", 
            "confidence": 5.3387073147949847e-16, 
            "word": "שבהם", 
            "gold_class": 0, 
            "predicted": "V01"
        }, 
        {
            "lang": 0, 
            "gold_pos": "", 
            "confidence": 1.0197334800466811e-09, 
            "word": "מכאן", 
            "gold_class": 0, 
            "predicted": "c"
        }, 
        {
            "lang": 0, 
            "gold_pos": "", 
            "confidence": 7.6937491271835664e-17, 
            "word": "אמרו", 
            "gold_class": 0, 
            "predicted": "V01"
        }, 
        {
            "lang": 0, 
            "gold_pos": "", 
            "confidence": 8.4108908136257504e-08, 
            "word": "המוכר", 
            "gold_class": 0, 
            "predicted": "V02"
        }, 
        {
            "lang": 0, 
            "gold_pos": "", 
            "confidence": 0.00018131662420721518, 
            "word": "שטרותיו", 
            "gold_class": 0, 
            "predicted": "V02"
        }, 
        {
            "lang": 0, 
            "gold_pos": "", 
            "confidence": 3.4662284135829278e-12, 
            "word": "לבשם", 
            "gold_class": 0, 
            "predicted": "a"
        }, 
        {
            "lang": 0, 
            "gold_pos": "", 
            "confidence": 3.0719103701425694e-14, 
            "word": "יש", 
            "gold_class": 0, 
            "predicted": "V01"
        }, 
        {
            "lang": 0, 
            "gold_pos": "", 
            "confidence": 2.0390783635743212e-15, 
            "word": "להם", 
            "gold_class": 0, 
            "predicted": "p01"
        }, 
        {
            "lang": 0, 
            "gold_pos": "", 
            "confidence": 6.9372452858196463e-12, 
            "word": "אונאה", 
            "gold_class": 0, 
            "predicted": "V01"
        }, 
        {
            "lang": 1, 
            "gold_pos": "", 
            "confidence": 0.0, 
            "word": "פשיטא", 
            "gold_class": 0, 
            "predicted": "A01"
        }, 
        {
            "lang": 1, 
            "gold_pos": "V03", 
            "confidence": 0.0, 
            "word": "לאפוקי", 
            "gold_class": 1, 
            "predicted": "V03"
        }, 
        {
            "lang": 1, 
            "gold_pos": "PN", 
            "confidence": 0.0, 
            "word": "מדרב", 
            "gold_class": 1, 
            "predicted": "PN"
        }, 
        {
            "lang": 1, 
            "gold_pos": "", 
            "confidence": 3.2514063968732271e-10, 
            "word": "כהנא", 
            "gold_class": 0, 
            "predicted": "a"
        }, 
        {
            "lang": 1, 
            "gold_pos": "", 
            "confidence": 0.0, 
            "word": "דאמר", 
            "gold_class": 0, 
            "predicted": "V01"
        }, 
        {
            "lang": 0, 
            "gold_pos": "", 
            "confidence": 3.3196207555480436e-18, 
            "word": "אין", 
            "gold_class": 0, 
            "predicted": "P"
        }, 
        {
            "lang": 0, 
            "gold_pos": "", 
            "confidence": 3.886270046271615e-14, 
            "word": "אונאה", 
            "gold_class": 0, 
            "predicted": "V01"
        }, 
        {
            "lang": 0, 
            "gold_pos": "", 
            "confidence": 7.6521586053817862e-08, 
            "word": "לפרוטות", 
            "gold_class": 0, 
            "predicted": "N02"
        }, 
        {
            "lang": 1, 
            "gold_pos": "", 
            "confidence": 0.0, 
            "word": "קא", 
            "gold_class": 0, 
            "predicted": "V03"
        }, 
        {
            "lang": 1, 
            "gold_pos": "", 
            "confidence": 0.0, 
            "word": "משמע", 
            "gold_class": 0, 
            "predicted": "V03"
        }, 
        {
            "lang": 1, 
            "gold_pos": "", 
            "confidence": 0.0, 
            "word": "לן", 
            "gold_class": 0, 
            "predicted": "V03"
        }, 
        {
            "lang": 0, 
            "gold_pos": "", 
            "confidence": 3.6874776189003493e-16, 
            "word": "יש", 
            "gold_class": 0, 
            "predicted": "V01"
        }, 
        {
            "lang": 0, 
            "gold_pos": "", 
            "confidence": 1.5059674239238316e-12, 
            "word": "אונאה", 
            "gold_class": 0, 
            "predicted": "N02"
        }, 
        {
            "lang": 0, 
            "gold_pos": "", 
            "confidence": 1.2294884520361298e-06, 
            "word": "לפרוטות", 
            "gold_class": 0, 
            "predicted": "N02"
        }, 
        {
            "lang": 0, 
            "gold_pos": "", 
            "confidence": 3.0259953622984299e-11, 
            "word": "הקדשות", 
            "gold_class": 0, 
            "predicted": "V01"
        }, 
        {
            "lang": 0, 
            "gold_pos": "", 
            "confidence": 2.3491480433935661e-10, 
            "word": "אמר", 
            "gold_class": 0, 
            "predicted": "V01"
        }, 
        {
            "lang": 1, 
            "gold_pos": "", 
            "confidence": 0.0, 
            "word": "קרא", 
            "gold_class": 0, 
            "predicted": "N02"
        }, 
        {
            "lang": 0, 
            "gold_pos": "", 
            "confidence": 2.6031562272741685e-11, 
            "word": "אחיו", 
            "gold_class": 0, 
            "predicted": "V03"
        }, 
        {
            "lang": 0, 
            "gold_pos": "", 
            "confidence": 1.5501995416729185e-14, 
            "word": "אחיו", 
            "gold_class": 0, 
            "predicted": "V03"
        }, 
        {
            "lang": 0, 
            "gold_pos": "", 
            "confidence": 2.9462301233038004e-12, 
            "word": "ולא", 
            "gold_class": 0, 
            "predicted": "a"
        }, 
        {
            "lang": 0, 
            "gold_pos": "", 
            "confidence": 1.1161381242415588e-09, 
            "word": "הקדש", 
            "gold_class": 0, 
            "predicted": "V02"
        }, 
        {
            "lang": 1, 
            "gold_pos": "V03", 
            "confidence": 0.0, 
            "word": "מתקיף", 
            "gold_class": 1, 
            "predicted": "V03"
        }, 
        {
            "lang": 0, 
            "gold_pos": "p02", 
            "confidence": 5.5465132991223809e-15, 
            "word": "לה", 
            "gold_class": 0, 
            "predicted": "p02"
        }, 
        {
            "lang": 1, 
            "gold_pos": "", 
            "confidence": 0.0, 
            "word": "רבה", 
            "gold_class": 0, 
            "predicted": "PN"
        }, 
        {
            "lang": 1, 
            "gold_pos": "", 
            "confidence": 1.24582114721385e-12, 
            "word": "בר", 
            "gold_class": 0, 
            "predicted": "N01"
        }, 
        {
            "lang": 0, 
            "gold_pos": "", 
            "confidence": 4.8837786531650161e-07, 
            "word": "ממל", 
            "gold_class": 0, 
            "predicted": "a"
        }, 
        {
            "lang": 0, 
            "gold_pos": "", 
            "confidence": 3.6684035043824714e-07, 
            "word": "כל", 
            "gold_class": 0, 
            "predicted": "N01"
        }, 
        {
            "lang": 1, 
            "gold_pos": "", 
            "confidence": 0.0, 
            "word": "היכא", 
            "gold_class": 0, 
            "predicted": "a"
        }, 
        {
            "lang": 0, 
            "gold_pos": "", 
            "confidence": 9.7645091273957376e-17, 
            "word": "דכתיב", 
            "gold_class": 0, 
            "predicted": "V01"
        }, 
        {
            "lang": 0, 
            "gold_pos": "", 
            "confidence": 1.0550527996132384e-11, 
            "word": "ידו", 
            "gold_class": 0, 
            "predicted": "V01"
        }, 
        {
            "lang": 0, 
            "gold_pos": "", 
            "confidence": 3.9255844846589614e-12, 
            "word": "ידו", 
            "gold_class": 0, 
            "predicted": "V01"
        }, 
        {
            "lang": 0, 
            "gold_pos": "", 
            "confidence": 6.4638819292282815e-11, 
            "word": "ממש", 
            "gold_class": 0, 
            "predicted": "a"
        }, 
        {
            "lang": 0, 
            "gold_pos": "", 
            "confidence": 3.297077293812862e-14, 
            "word": "הוא", 
            "gold_class": 0, 
            "predicted": "V01"
        }, 
        {
            "lang": 0, 
            "gold_pos": "", 
            "confidence": 8.1793221011393956e-13, 
            "word": "אלא", 
            "gold_class": 0, 
            "predicted": "c"
        }, 
        {
            "lang": 0, 
            "gold_pos": "", 
            "confidence": 4.6578398212962398e-14, 
            "word": "מעתה", 
            "gold_class": 0, 
            "predicted": "V03"
        }, 
        {
            "lang": 0, 
            "gold_pos": "", 
            "confidence": 2.2205253262354596e-17, 
            "word": "דכתיב", 
            "gold_class": 0, 
            "predicted": "V01"
        }, 
        {
            "lang": 0, 
            "gold_pos": "", 
            "confidence": 1.3479172778593462e-16, 
            "word": "ויקח", 
            "gold_class": 0, 
            "predicted": "V01"
        }, 
        {
            "lang": 0, 
            "gold_pos": "", 
            "confidence": 5.4649539310024141e-17, 
            "word": "את", 
            "gold_class": 0, 
            "predicted": "a"
        }, 
        {
            "lang": 0, 
            "gold_pos": "", 
            "confidence": 7.126097777062375e-05, 
            "word": "כל", 
            "gold_class": 0, 
            "predicted": "N02"
        }, 
        {
            "lang": 0, 
            "gold_pos": "", 
            "confidence": 3.7349355491410699e-09, 
            "word": "ארצו", 
            "gold_class": 0, 
            "predicted": "N05"
        }, 
        {
            "lang": 0, 
            "gold_pos": "", 
            "confidence": 2.6990383105289149e-10, 
            "word": "מידו", 
            "gold_class": 0, 
            "predicted": "c"
        }, 
        {
            "lang": 1, 
            "gold_pos": "", 
            "confidence": 0.0, 
            "word": "הכי", 
            "gold_class": 0, 
            "predicted": "a"
        }, 
        {
            "lang": 1, 
            "gold_pos": "", 
            "confidence": 0.0, 
            "word": "נמי", 
            "gold_class": 0, 
            "predicted": "a"
        }, 
        {
            "lang": 1, 
            "gold_pos": "", 
            "confidence": 0.0, 
            "word": "דכל", 
            "gold_class": 0, 
            "predicted": "N01"
        }, 
        {
            "lang": 1, 
            "gold_pos": "", 
            "confidence": 0.0, 
            "word": "ארעא", 
            "gold_class": 0, 
            "predicted": "N02"
        }, 
        {
            "lang": 1, 
            "gold_pos": "", 
            "confidence": 0.0, 
            "word": "בידיה", 
            "gold_class": 0, 
            "predicted": "N02"
        }, 
        {
            "lang": 1, 
            "gold_pos": "", 
            "confidence": 0.0, 
            "word": "הוה", 
            "gold_class": 0, 
            "predicted": "V01"
        }, 
        {
            "lang": 1, 
            "gold_pos": "", 
            "confidence": 0.0, 
            "word": "נקיט", 
            "gold_class": 0, 
            "predicted": "V01"
        }, 
        {
            "lang": 0, 
            "gold_pos": "N02", 
            "confidence": 6.4468895480741467e-17, 
            "word": "לה", 
            "gold_class": 0, 
            "predicted": "p02"
        }, 
        {
            "lang": 0, 
            "gold_pos": "", 
            "confidence": 8.2233333728533678e-11, 
            "word": "אלא", 
            "gold_class": 0, 
            "predicted": "c"
        }, 
        {
            "lang": 0, 
            "gold_pos": "", 
            "confidence": 3.7585944180271646e-07, 
            "word": "מרשותו", 
            "gold_class": 0, 
            "predicted": "V02"
        }, 
        {
            "lang": 1, 
            "gold_pos": "", 
            "confidence": 0.0, 
            "word": "הכא", 
            "gold_class": 0, 
            "predicted": "a"
        }, 
        {
            "lang": 1, 
            "gold_pos": "a", 
            "confidence": 0.0, 
            "word": "נמי", 
            "gold_class": 1, 
            "predicted": "a"
        }, 
        {
            "lang": 0, 
            "gold_pos": "", 
            "confidence": 3.1344679251694089e-12, 
            "word": "מרשותו", 
            "gold_class": 0, 
            "predicted": "V02"
        }, 
        {
            "lang": 0, 
            "gold_pos": "", 
            "confidence": 9.5003788292080057e-11, 
            "word": "וכל", 
            "gold_class": 0, 
            "predicted": "a"
        }, 
        {
            "lang": 1, 
            "gold_pos": "", 
            "confidence": 0.0, 
            "word": "היכא", 
            "gold_class": 0, 
            "predicted": "a"
        }, 
        {
            "lang": 0, 
            "gold_pos": "", 
            "confidence": 5.5409046703076927e-16, 
            "word": "דכתיב", 
            "gold_class": 0, 
            "predicted": "V01"
        }, 
        {
            "lang": 0, 
            "gold_pos": "", 
            "confidence": 8.7908292422494468e-09, 
            "word": "ידו", 
            "gold_class": 0, 
            "predicted": "V01"
        }, 
        {
            "lang": 1, 
            "gold_pos": "", 
            "confidence": 0.0, 
            "word": "לאו", 
            "gold_class": 0, 
            "predicted": "a"
        }, 
        {
            "lang": 0, 
            "gold_pos": "", 
            "confidence": 1.042179004190827e-14, 
            "word": "ידו", 
            "gold_class": 0, 
            "predicted": "V01"
        }, 
        {
            "lang": 0, 
            "gold_pos": "", 
            "confidence": 7.0977064991425996e-10, 
            "word": "ממש", 
            "gold_class": 0, 
            "predicted": "a"
        }, 
        {
            "lang": 0, 
            "gold_pos": "", 
            "confidence": 5.3042963397241745e-17, 
            "word": "הוא", 
            "gold_class": 0, 
            "predicted": "V01"
        }, 
        {
            "lang": 1, 
            "gold_pos": "", 
            "confidence": 0.0, 
            "word": "והתניא", 
            "gold_class": 0, 
            "predicted": "V01"
        }, 
        {
            "lang": 0, 
            "gold_pos": "", 
            "confidence": 1.2119546922385625e-14, 
            "word": "אם", 
            "gold_class": 0, 
            "predicted": "a"
        }, 
        {
            "lang": 0, 
            "gold_pos": "", 
            "confidence": 8.4846619363137526e-11, 
            "word": "המצא", 
            "gold_class": 0, 
            "predicted": "V02"
        }, 
        {
            "lang": 0, 
            "gold_pos": "", 
            "confidence": 4.6928519731585684e-09, 
            "word": "תמצא", 
            "gold_class": 0, 
            "predicted": "N02"
        }, 
        {
            "lang": 0, 
            "gold_pos": "", 
            "confidence": 5.0320195089250807e-09, 
            "word": "בידו", 
            "gold_class": 0, 
            "predicted": "V01"
        }, 
        {
            "lang": 0, 
            "gold_pos": "", 
            "confidence": 1.2675312937327511e-11, 
            "word": "אין", 
            "gold_class": 0, 
            "predicted": "P"
        }, 
        {
            "lang": 0, 
            "gold_pos": "", 
            "confidence": 3.2521847525287834e-11, 
            "word": "לי", 
            "gold_class": 0, 
            "predicted": "V01"
        }, 
        {
            "lang": 0, 
            "gold_pos": "", 
            "confidence": 5.2706672008726131e-12, 
            "word": "אלא", 
            "gold_class": 0, 
            "predicted": "a"
        }, 
        {
            "lang": 0, 
            "gold_pos": "", 
            "confidence": 1.1698770139951262e-15, 
            "word": "ידו", 
            "gold_class": 0, 
            "predicted": "V01"
        }, 
        {
            "lang": 0, 
            "gold_pos": "", 
            "confidence": 1.5709381740733107e-12, 
            "word": "גגו", 
            "gold_class": 0, 
            "predicted": "V01"
        }, 
        {
            "lang": 0, 
            "gold_pos": "", 
            "confidence": 9.8957152286025951e-06, 
            "word": "חצירו", 
            "gold_class": 0, 
            "predicted": "A05"
        }, 
        {
            "lang": 1, 
            "gold_pos": "", 
            "confidence": 3.1161987839460461e-07, 
            "word": "וקרפיפו", 
            "gold_class": 0, 
            "predicted": "A05"
        }, 
        {
            "lang": 0, 
            "gold_pos": "", 
            "confidence": 9.175825466243516e-15, 
            "word": "מנין", 
            "gold_class": 0, 
            "predicted": "P"
        }, 
        {
            "lang": 0, 
            "gold_pos": "", 
            "confidence": 2.4098033000845123e-07, 
            "word": "תלמוד", 
            "gold_class": 0, 
            "predicted": "V01"
        }, 
        {
            "lang": 0, 
            "gold_pos": "", 
            "confidence": 3.3168144661980832e-09, 
            "word": "לומר", 
            "gold_class": 0, 
            "predicted": "PN"
        }, 
        {
            "lang": 0, 
            "gold_pos": "", 
            "confidence": 5.1067309807196553e-14, 
            "word": "אם", 
            "gold_class": 0, 
            "predicted": "V03"
        }, 
        {
            "lang": 0, 
            "gold_pos": "", 
            "confidence": 4.72450987075488e-09, 
            "word": "המצא", 
            "gold_class": 0, 
            "predicted": "N02"
        }, 
        {
            "lang": 0, 
            "gold_pos": "", 
            "confidence": 7.0710679700576114e-10, 
            "word": "תמצא", 
            "gold_class": 0, 
            "predicted": "N02"
        }, 
        {
            "lang": 0, 
            "gold_pos": "", 
            "confidence": 0.0016112782567256859, 
            "word": "מכל", 
            "gold_class": 0, 
            "predicted": "V08"
        }, 
        {
            "lang": 0, 
            "gold_pos": "", 
            "confidence": 5.1452985943596968e-13, 
            "word": "מקום", 
            "gold_class": 0, 
            "predicted": "V03"
        }, 
        {
            "lang": 1, 
            "gold_pos": "", 
            "confidence": 0.0, 
            "word": "טעמא", 
            "gold_class": 0, 
            "predicted": "N02"
        }, 
        {
            "lang": 1, 
            "gold_pos": "", 
            "confidence": 0.0, 
            "word": "דכתב", 
            "gold_class": 0, 
            "predicted": "V01"
        }, 
        {
            "lang": 1, 
            "gold_pos": "", 
            "confidence": 0.0, 
            "word": "רחמנא", 
            "gold_class": 0, 
            "predicted": "N02"
        }, 
        {
            "lang": 0, 
            "gold_pos": "", 
            "confidence": 4.6154334247853351e-13, 
            "word": "אם", 
            "gold_class": 0, 
            "predicted": "a"
        }, 
        {
            "lang": 0, 
            "gold_pos": "", 
            "confidence": 1.3645302183062313e-09, 
            "word": "המצא", 
            "gold_class": 0, 
            "predicted": "V01"
        }, 
        {
            "lang": 0, 
            "gold_pos": "", 
            "confidence": 2.9708140399947447e-09, 
            "word": "תמצא", 
            "gold_class": 0, 
            "predicted": "N02"
        }, 
        {
            "lang": 1, 
            "gold_pos": "", 
            "confidence": 0.0, 
            "word": "הא", 
            "gold_class": 0, 
            "predicted": "I"
        }, 
        {
            "lang": 1, 
            "gold_pos": "", 
            "confidence": 0.0, 
            "word": "לאו", 
            "gold_class": 0, 
            "predicted": "a"
        }, 
        {
            "lang": 1, 
            "gold_pos": "", 
            "confidence": 0.0, 
            "word": "הכי", 
            "gold_class": 0, 
            "predicted": "a"
        }, 
        {
            "lang": 1, 
            "gold_pos": "", 
            "confidence": 0.0, 
            "word": "הוה", 
            "gold_class": 0, 
            "predicted": "V01"
        }, 
        {
            "lang": 1, 
            "gold_pos": "", 
            "confidence": 0.0, 
            "word": "אמינא", 
            "gold_class": 0, 
            "predicted": "V01"
        }, 
        {
            "lang": 0, 
            "gold_pos": "", 
            "confidence": 2.5773236832896635e-12, 
            "word": "כל", 
            "gold_class": 0, 
            "predicted": "c"
        }, 
        {
            "lang": 1, 
            "gold_pos": "", 
            "confidence": 0.0, 
            "word": "היכא", 
            "gold_class": 0, 
            "predicted": "a"
        }, 
        {
            "lang": 1, 
            "gold_pos": "", 
            "confidence": 0.0, 
            "word": "דכתב", 
            "gold_class": 0, 
            "predicted": "V01"
        }, 
        {
            "lang": 0, 
            "gold_pos": "", 
            "confidence": 2.7662469672578641e-13, 
            "word": "ידו", 
            "gold_class": 0, 
            "predicted": "V01"
        }, 
        {
            "lang": 0, 
            "gold_pos": "", 
            "confidence": 2.7833004202749391e-12, 
            "word": "ידו", 
            "gold_class": 0, 
            "predicted": "V01"
        }, 
        {
            "lang": 0, 
            "gold_pos": "", 
            "confidence": 1.6032759027737113e-10, 
            "word": "ממש", 
            "gold_class": 0, 
            "predicted": "a"
        }, 
        {
            "lang": 0, 
            "gold_pos": "", 
            "confidence": 1.3003785445030706e-13, 
            "word": "הוא", 
            "gold_class": 0, 
            "predicted": "V01"
        }, 
        {
            "lang": 1, 
            "gold_pos": "", 
            "confidence": 0.0, 
            "word": "ותו", 
            "gold_class": 0, 
            "predicted": "a"
        }, 
        {
            "lang": 1, 
            "gold_pos": "", 
            "confidence": 0.0, 
            "word": "תניא", 
            "gold_class": 0, 
            "predicted": "V01"
        }, 
        {
            "lang": 0, 
            "gold_pos": "", 
            "confidence": 1.9744478165966093e-10, 
            "word": "ונתן", 
            "gold_class": 0, 
            "predicted": "a"
        }, 
        {
            "lang": 0, 
            "gold_pos": "", 
            "confidence": 4.5699960078378755e-16, 
            "word": "בידה", 
            "gold_class": 0, 
            "predicted": "p02"
        }, 
        {
            "lang": 0, 
            "gold_pos": "", 
            "confidence": 1.8593299026617814e-09, 
            "word": "אין", 
            "gold_class": 0, 
            "predicted": "P"
        }, 
        {
            "lang": 0, 
            "gold_pos": "", 
            "confidence": 1.9200920242473979e-09, 
            "word": "לי", 
            "gold_class": 0, 
            "predicted": "V01"
        }, 
        {
            "lang": 0, 
            "gold_pos": "", 
            "confidence": 5.2827885919943061e-13, 
            "word": "אלא", 
            "gold_class": 0, 
            "predicted": "c"
        }, 
        {
            "lang": 0, 
            "gold_pos": "", 
            "confidence": 1.3192013347456897e-12, 
            "word": "ידה", 
            "gold_class": 0, 
            "predicted": "P"
        }, 
        {
            "lang": 0, 
            "gold_pos": "", 
            "confidence": 1.2282730244256431e-13, 
            "word": "גגה", 
            "gold_class": 0, 
            "predicted": "V01"
        }, 
        {
            "lang": 0, 
            "gold_pos": "", 
            "confidence": 1.5875055714349167e-07, 
            "word": "חצירה", 
            "gold_class": 0, 
            "predicted": "V01"
        }, 
        {
            "lang": 0, 
            "gold_pos": "", 
            "confidence": 5.4904575890880147e-09, 
            "word": "וקרפיפה", 
            "gold_class": 0, 
            "predicted": "V01"
        }, 
        {
            "lang": 0, 
            "gold_pos": "", 
            "confidence": 1.3176171274332492e-16, 
            "word": "מנין", 
            "gold_class": 0, 
            "predicted": "P"
        }, 
        {
            "lang": 0, 
            "gold_pos": "", 
            "confidence": 3.6549455200125392e-08, 
            "word": "תלמוד", 
            "gold_class": 0, 
            "predicted": "V01"
        }, 
        {
            "lang": 0, 
            "gold_pos": "", 
            "confidence": 3.2838324909915964e-09, 
            "word": "לומר", 
            "gold_class": 0, 
            "predicted": "PN"
        }, 
        {
            "lang": 0, 
            "gold_pos": "", 
            "confidence": 3.2729517953774974e-12, 
            "word": "ונתן", 
            "gold_class": 0, 
            "predicted": "V03"
        }, 
        {
            "lang": 0, 
            "gold_pos": "", 
            "confidence": 3.2571472937652147e-06, 
            "word": "מכל", 
            "gold_class": 0, 
            "predicted": "c"
        }, 
        {
            "lang": 0, 
            "gold_pos": "", 
            "confidence": 4.9959963689280569e-12, 
            "word": "מקום", 
            "gold_class": 0, 
            "predicted": "V03"
        }, 
        {
            "lang": 1, 
            "gold_pos": "", 
            "confidence": 0.0, 
            "word": "טעמא", 
            "gold_class": 0, 
            "predicted": "N02"
        }, 
        {
            "lang": 1, 
            "gold_pos": "", 
            "confidence": 0.0, 
            "word": "דכתב", 
            "gold_class": 0, 
            "predicted": "V01"
        }, 
        {
            "lang": 1, 
            "gold_pos": "", 
            "confidence": 0.0, 
            "word": "רחמנא", 
            "gold_class": 0, 
            "predicted": "N02"
        }, 
        {
            "lang": 0, 
            "gold_pos": "", 
            "confidence": 1.462995992493333e-12, 
            "word": "ונתן", 
            "gold_class": 0, 
            "predicted": "V03"
        }, 
        {
            "lang": 1, 
            "gold_pos": "", 
            "confidence": 0.0, 
            "word": "הא", 
            "gold_class": 0, 
            "predicted": "I"
        }, 
        {
            "lang": 1, 
            "gold_pos": "", 
            "confidence": 0.0, 
            "word": "לאו", 
            "gold_class": 0, 
            "predicted": "a"
        }, 
        {
            "lang": 1, 
            "gold_pos": "", 
            "confidence": 0.0, 
            "word": "הכי", 
            "gold_class": 0, 
            "predicted": "a"
        }, 
        {
            "lang": 1, 
            "gold_pos": "", 
            "confidence": 0.0, 
            "word": "הוה", 
            "gold_class": 0, 
            "predicted": "V01"
        }, 
        {
            "lang": 1, 
            "gold_pos": "", 
            "confidence": 0.0, 
            "word": "אמינא", 
            "gold_class": 0, 
            "predicted": "V01"
        }, 
        {
            "lang": 0, 
            "gold_pos": "", 
            "confidence": 3.033960494334829e-12, 
            "word": "כל", 
            "gold_class": 0, 
            "predicted": "c"
        }, 
        {
            "lang": 1, 
            "gold_pos": "", 
            "confidence": 0.0, 
            "word": "היכא", 
            "gold_class": 0, 
            "predicted": "a"
        }, 
        {
            "lang": 1, 
            "gold_pos": "", 
            "confidence": 0.0, 
            "word": "דכתב", 
            "gold_class": 0, 
            "predicted": "V01"
        }, 
        {
            "lang": 0, 
            "gold_pos": "", 
            "confidence": 8.0226503674266489e-13, 
            "word": "ידו", 
            "gold_class": 0, 
            "predicted": "V01"
        }, 
        {
            "lang": 0, 
            "gold_pos": "", 
            "confidence": 6.6275960334811982e-13, 
            "word": "ידו", 
            "gold_class": 0, 
            "predicted": "V01"
        }, 
        {
            "lang": 0, 
            "gold_pos": "", 
            "confidence": 7.4353592418583377e-10, 
            "word": "ממש", 
            "gold_class": 0, 
            "predicted": "a"
        }, 
        {
            "lang": 0, 
            "gold_pos": "", 
            "confidence": 6.0748639612452465e-13, 
            "word": "אלא", 
            "gold_class": 0, 
            "predicted": "a"
        }, 
        {
            "lang": 0, 
            "gold_pos": "", 
            "confidence": 5.2079055407630971e-12, 
            "word": "כל", 
            "gold_class": 0, 
            "predicted": "V01"
        }, 
        {
            "lang": 0, 
            "gold_pos": "", 
            "confidence": 3.6644420672840432e-14, 
            "word": "ידו", 
            "gold_class": 0, 
            "predicted": "V01"
        }, 
        {
            "lang": 0, 
            "gold_pos": "", 
            "confidence": 1.061669614024755e-12, 
            "word": "ידו", 
            "gold_class": 0, 
            "predicted": "V01"
        }, 
        {
            "lang": 0, 
            "gold_pos": "", 
            "confidence": 1.6749573820078743e-11, 
            "word": "ממש", 
            "gold_class": 0, 
            "predicted": "a"
        }, 
        {
            "lang": 0, 
            "gold_pos": "", 
            "confidence": 9.854063580332097e-15, 
            "word": "הוא", 
            "gold_class": 0, 
            "predicted": "V01"
        }, 
        {
            "lang": 1, 
            "gold_pos": "", 
            "confidence": 0.0, 
            "word": "ושאני", 
            "gold_class": 0, 
            "predicted": "*BOS*"
        }, 
        {
            "lang": 1, 
            "gold_pos": "", 
            "confidence": 0.0, 
            "word": "התם", 
            "gold_class": 0, 
            "predicted": "*BOS*"
        }, 
        {
            "lang": 1, 
            "gold_pos": "", 
            "confidence": 0.0, 
            "word": "דליכא", 
            "gold_class": 0, 
            "predicted": "*BOS*"
        }, 
        {
            "lang": 1, 
            "gold_pos": "", 
            "confidence": 0.0, 
            "word": "למימר", 
            "gold_class": 0, 
            "predicted": "*BOS*"
        }, 
        {
            "lang": 1, 
            "gold_pos": "", 
            "confidence": 0.0, 
            "word": "הכי", 
            "gold_class": 0, 
            "predicted": "*BOS*"
        }, 
        {
            "lang": 0, 
            "gold_pos": "", 
            "confidence": 3.5062998532833691e-09, 
            "word": "אלא", 
            "gold_class": 0, 
            "predicted": "c"
        }, 
        {
            "lang": 0, 
            "gold_pos": "", 
            "confidence": 4.6866882779101856e-07, 
            "word": "ברשותו", 
            "gold_class": 0, 
            "predicted": "N02"
        }, 
        {
            "lang": 1, 
            "gold_pos": "", 
            "confidence": 0.0, 
            "word": "בעי", 
            "gold_class": 0, 
            "predicted": "*BOS*"
        }, 
        {
            "lang": 0, 
            "gold_pos": "", 
            "confidence": 5.8658440111289779e-05, 
            "word": "רבי", 
            "gold_class": 0, 
            "predicted": "A03"
        }, 
        {
            "lang": 1, 
            "gold_pos": "", 
            "confidence": 1.7121405698515878e-10, 
            "word": "זירא", 
            "gold_class": 0, 
            "predicted": "N02"
        }, 
        {
            "lang": 0, 
            "gold_pos": "", 
            "confidence": 8.2368676344066625e-10, 
            "word": "שכירות", 
            "gold_class": 0, 
            "predicted": "V01"
        }, 
        {
            "lang": 0, 
            "gold_pos": "", 
            "confidence": 4.6128390646801578e-14, 
            "word": "יש", 
            "gold_class": 0, 
            "predicted": "V01"
        }, 
        {
            "lang": 0, 
            "gold_pos": "", 
            "confidence": 1.1235277630112002e-10, 
            "word": "לו", 
            "gold_class": 0, 
            "predicted": "p01"
        }, 
        {
            "lang": 0, 
            "gold_pos": "", 
            "confidence": 2.3155664243413175e-13, 
            "word": "אונאה", 
            "gold_class": 0, 
            "predicted": "V01"
        }, 
        {
            "lang": 0, 
            "gold_pos": "", 
            "confidence": 2.6708787453816407e-10, 
            "word": "או", 
            "gold_class": 0, 
            "predicted": "a"
        }, 
        {
            "lang": 0, 
            "gold_pos": "", 
            "confidence": 8.3699729098553469e-09, 
            "word": "אין", 
            "gold_class": 0, 
            "predicted": "P"
        }, 
        {
            "lang": 0, 
            "gold_pos": "", 
            "confidence": 8.9298354155304521e-12, 
            "word": "לו", 
            "gold_class": 0, 
            "predicted": "p01"
        }, 
        {
            "lang": 0, 
            "gold_pos": "", 
            "confidence": 2.2996425478106952e-12, 
            "word": "אונאה", 
            "gold_class": 0, 
            "predicted": "N02"
        }, 
        {
            "lang": 0, 
            "gold_pos": "", 
            "confidence": 4.5000691784244183e-05, 
            "word": "ממכר", 
            "gold_class": 0, 
            "predicted": "V03"
        }, 
        {
            "lang": 0, 
            "gold_pos": "", 
            "confidence": 1.3080785681022051e-12, 
            "word": "אמר", 
            "gold_class": 0, 
            "predicted": "V01"
        }, 
        {
            "lang": 1, 
            "gold_pos": "", 
            "confidence": 0.0, 
            "word": "רחמנא", 
            "gold_class": 0, 
            "predicted": "*BOS*"
        }, 
        {
            "lang": 0, 
            "gold_pos": "", 
            "confidence": 5.6542776724168186e-12, 
            "word": "אבל", 
            "gold_class": 0, 
            "predicted": "V03"
        }, 
        {
            "lang": 0, 
            "gold_pos": "", 
            "confidence": 2.5917264973214333e-15, 
            "word": "לא", 
            "gold_class": 0, 
            "predicted": "a"
        }, 
        {
            "lang": 0, 
            "gold_pos": "", 
            "confidence": 1.9706317095253821e-11, 
            "word": "שכירות", 
            "gold_class": 0, 
            "predicted": "V01"
        }, 
        {
            "lang": 0, 
            "gold_pos": "", 
            "confidence": 2.5038040622962467e-10, 
            "word": "או", 
            "gold_class": 0, 
            "predicted": "c"
        }, 
        {
            "lang": 1, 
            "gold_pos": "", 
            "confidence": 0.0, 
            "word": "דלמא", 
            "gold_class": 0, 
            "predicted": "*BOS*"
        }, 
        {
            "lang": 0, 
            "gold_pos": "", 
            "confidence": 6.2851858477229008e-15, 
            "word": "לא", 
            "gold_class": 0, 
            "predicted": "a"
        }, 
        {
            "lang": 1, 
            "gold_pos": "", 
            "confidence": 0.0, 
            "word": "שנא", 
            "gold_class": 0, 
            "predicted": "*BOS*"
        }, 
        {
            "lang": 0, 
            "gold_pos": "", 
            "confidence": 1.8353398642532217e-18, 
            "word": "אמר", 
            "gold_class": 0, 
            "predicted": "V01"
        }, 
        {
            "lang": 1, 
            "gold_pos": "", 
            "confidence": 3.9932098690039701e-20, 
            "word": "ליה", 
            "gold_class": 0, 
            "predicted": "*BOS*"
        }, 
        {
            "lang": 1, 
            "gold_pos": "", 
            "confidence": 4.7465856937111305e-05, 
            "word": "אביי", 
            "gold_class": 0, 
            "predicted": "PN"
        }, 
        {
            "lang": 0, 
            "gold_pos": "", 
            "confidence": 4.0483156046264481e-13, 
            "word": "מי", 
            "gold_class": 0, 
            "predicted": "a"
        }, 
        {
            "lang": 1, 
            "gold_pos": "", 
            "confidence": 0.0, 
            "word": "כתיב", 
            "gold_class": 0, 
            "predicted": "*BOS*"
        }, 
        {
            "lang": 0, 
            "gold_pos": "", 
            "confidence": 2.1399610073148099e-08, 
            "word": "ממכר", 
            "gold_class": 0, 
            "predicted": "c"
        }, 
        {
            "lang": 0, 
            "gold_pos": "", 
            "confidence": 1.4754377100176827e-11, 
            "word": "לעולם", 
            "gold_class": 0, 
            "predicted": "V03"
        }, 
        {
            "lang": 0, 
            "gold_pos": "", 
            "confidence": 9.8732102050843212e-09, 
            "word": "ממכר", 
            "gold_class": 0, 
            "predicted": "V04"
        }, 
        {
            "lang": 1, 
            "gold_pos": "", 
            "confidence": 0.0, 
            "word": "סתמא", 
            "gold_class": 0, 
            "predicted": "*BOS*"
        }, 
        {
            "lang": 1, 
            "gold_pos": "", 
            "confidence": 0.0, 
            "word": "כתיב", 
            "gold_class": 0, 
            "predicted": "*BOS*"
        }, 
        {
            "lang": 1, 
            "gold_pos": "", 
            "confidence": 0.0, 
            "word": "והאי", 
            "gold_class": 0, 
            "predicted": "*BOS*"
        }, 
        {
            "lang": 1, 
            "gold_pos": "", 
            "confidence": 0.0, 
            "word": "נמי", 
            "gold_class": 0, 
            "predicted": "*BOS*"
        }, 
        {
            "lang": 1, 
            "gold_pos": "", 
            "confidence": 0.0, 
            "word": "ביומיה", 
            "gold_class": 0, 
            "predicted": "*BOS*"
        }, 
        {
            "lang": 0, 
            "gold_pos": "", 
            "confidence": 3.4179820420773702e-10, 
            "word": "מכירה", 
            "gold_class": 0, 
            "predicted": "V01"
        }, 
        {
            "lang": 0, 
            "gold_pos": "P", 
            "confidence": 3.2997570791361484e-11, 
            "word": "היא", 
            "gold_class": 0, 
            "predicted": "V01"
        }, 
        {
            "lang": 1, 
            "gold_pos": "", 
            "confidence": 0.0, 
            "word": "בעי", 
            "gold_class": 0, 
            "predicted": "*BOS*"
        }, 
        {
            "lang": 1, 
            "gold_pos": "", 
            "confidence": 0.0, 
            "word": "רבא", 
            "gold_class": 0, 
            "predicted": "*BOS*"
        }, 
        {
            "lang": 0, 
            "gold_pos": "", 
            "confidence": 1.8779108057583517e-12, 
            "word": "חטין", 
            "gold_class": 0, 
            "predicted": "V01"
        }, 
        {
            "lang": 0, 
            "gold_pos": "", 
            "confidence": 3.571231437416515e-11, 
            "word": "וזרען", 
            "gold_class": 0, 
            "predicted": "V01"
        }, 
        {
            "lang": 0, 
            "gold_pos": "", 
            "confidence": 1.6468698161758334e-12, 
            "word": "בקרקע", 
            "gold_class": 0, 
            "predicted": "N05"
        }, 
        {
            "lang": 1, 
            "gold_pos": "", 
            "confidence": 0.0, 
            "word": "מהו", 
            "gold_class": 0, 
            "predicted": "*BOS*"
        }, 
        {
            "lang": 0, 
            "gold_pos": "", 
            "confidence": 5.5127794594926456e-16, 
            "word": "יש", 
            "gold_class": 0, 
            "predicted": "V01"
        }, 
        {
            "lang": 0, 
            "gold_pos": "", 
            "confidence": 1.3955092999534864e-14, 
            "word": "להם", 
            "gold_class": 0, 
            "predicted": "p01"
        }, 
        {
            "lang": 0, 
            "gold_pos": "", 
            "confidence": 7.8091734520406018e-13, 
            "word": "אונאה", 
            "gold_class": 0, 
            "predicted": "V01"
        }, 
        {
            "lang": 0, 
            "gold_pos": "c", 
            "confidence": 5.6221116005254328e-11, 
            "word": "או", 
            "gold_class": 0, 
            "predicted": "c"
        }, 
        {
            "lang": 0, 
            "gold_pos": "", 
            "confidence": 1.652642708137014e-10, 
            "word": "אין", 
            "gold_class": 0, 
            "predicted": "c"
        }, 
        {
            "lang": 0, 
            "gold_pos": "p01", 
            "confidence": 1.2882490652175661e-12, 
            "word": "להם", 
            "gold_class": 0, 
            "predicted": "p01"
        }, 
        {
            "lang": 0, 
            "gold_pos": "", 
            "confidence": 3.9718097276507864e-12, 
            "word": "אונאה", 
            "gold_class": 0, 
            "predicted": "N02"
        }, 
        {
            "lang": 1, 
            "gold_pos": "", 
            "confidence": 0.0, 
            "word": "כמאן", 
            "gold_class": 0, 
            "predicted": "*BOS*"
        }, 
        {
            "lang": 1, 
            "gold_pos": "", 
            "confidence": 1.2667028531949992e-06, 
            "word": "דשדיין", 
            "gold_class": 0, 
            "predicted": "V01"
        }, 
        {
            "lang": 1, 
            "gold_pos": "", 
            "confidence": 0.0, 
            "word": "בכדא", 
            "gold_class": 0, 
            "predicted": "*BOS*"
        }, 
        {
            "lang": 1, 
            "gold_pos": "", 
            "confidence": 0.0, 
            "word": "דמיין", 
            "gold_class": 0, 
            "predicted": "*BOS*"
        }, 
        {
            "lang": 0, 
            "gold_pos": "", 
            "confidence": 1.2198672044388789e-15, 
            "word": "ויש", 
            "gold_class": 0, 
            "predicted": "V01"
        }, 
        {
            "lang": 0, 
            "gold_pos": "", 
            "confidence": 1.4672949029774275e-14, 
            "word": "להם", 
            "gold_class": 0, 
            "predicted": "p01"
        }, 
        {
            "lang": 0, 
            "gold_pos": "", 
            "confidence": 1.7568450318445741e-12, 
            "word": "אונאה", 
            "gold_class": 0, 
            "predicted": "N02"
        }, 
        {
            "lang": 0, 
            "gold_pos": "", 
            "confidence": 2.3600401289603564e-09, 
            "word": "או", 
            "gold_class": 0, 
            "predicted": "a"
        }, 
        {
            "lang": 1, 
            "gold_pos": "", 
            "confidence": 0.0, 
            "word": "דלמא", 
            "gold_class": 0, 
            "predicted": "*BOS*"
        }, 
        {
            "lang": 1, 
            "gold_pos": "", 
            "confidence": 1.3007281459585235e-15, 
            "word": "בטלינהו", 
            "gold_class": 0, 
            "predicted": "V01"
        }, 
        {
            "lang": 0, 
            "gold_pos": "", 
            "confidence": 4.4683380835116229e-16, 
            "word": "על", 
            "gold_class": 0, 
            "predicted": "V01"
        }, 
        {
            "lang": 1, 
            "gold_pos": "", 
            "confidence": 0.0, 
            "word": "גב", 
            "gold_class": 0, 
            "predicted": "*BOS*"
        }, 
        {
            "lang": 1, 
            "gold_pos": "N02", 
            "confidence": 0.0, 
            "word": "ארעא", 
            "gold_class": 1, 
            "predicted": "*BOS*"
        }, 
        {
            "lang": 1, 
            "gold_pos": "a", 
            "confidence": 0.0, 
            "word": "היכי", 
            "gold_class": 1, 
            "predicted": "*BOS*"
        }, 
        {
            "lang": 1, 
            "gold_pos": "V01", 
            "confidence": 0.0, 
            "word": "דמי", 
            "gold_class": 1, 
            "predicted": "*BOS*"
        }, 
        {
            "lang": 1, 
            "gold_pos": "V01", 
            "confidence": 0.0, 
            "word": "אילימא", 
            "gold_class": 1, 
            "predicted": "*BOS*"
        }, 
        {
            "lang": 1, 
            "gold_pos": "", 
            "confidence": 0.0, 
            "word": "דאמר", 
            "gold_class": 0, 
            "predicted": "*BOS*"
        }, 
        {
            "lang": 1, 
            "gold_pos": "", 
            "confidence": 0.0, 
            "word": "איהו", 
            "gold_class": 0, 
            "predicted": "*BOS*"
        }, 
        {
            "lang": 1, 
            "gold_pos": "V01", 
            "confidence": 0.0, 
            "word": "שדאי", 
            "gold_class": 1, 
            "predicted": "*BOS*"
        }, 
        {
            "lang": 0, 
            "gold_pos": "p02", 
            "confidence": 1.8204427598031058e-15, 
            "word": "בה", 
            "gold_class": 0, 
            "predicted": "p02"
        }, 
        {
            "lang": 1, 
            "gold_pos": "n02", 
            "confidence": 0.0, 
            "word": "שיתא", 
            "gold_class": 1, 
            "predicted": "*BOS*"
        }, 
        {
            "lang": 0, 
            "gold_pos": "V01", 
            "confidence": 2.6371015937011463e-10, 
            "word": "ואתו", 
            "gold_class": 0, 
            "predicted": "V01"
        }, 
        {
            "lang": 1, 
            "gold_pos": "N05", 
            "confidence": 0.0, 
            "word": "סהדי", 
            "gold_class": 1, 
            "predicted": "*BOS*"
        }, 
        {
            "lang": 1, 
            "gold_pos": "", 
            "confidence": 0.0, 
            "word": "ואמרי", 
            "gold_class": 0, 
            "predicted": "*BOS*"
        }, 
        {
            "lang": 1, 
            "gold_pos": "a", 
            "confidence": 0.0, 
            "word": "דלא", 
            "gold_class": 1, 
            "predicted": "*BOS*"
        }, 
        {
            "lang": 1, 
            "gold_pos": "V01", 
            "confidence": 0.0, 
            "word": "שדא", 
            "gold_class": 1, 
            "predicted": "*BOS*"
        }, 
        {
            "lang": 0, 
            "gold_pos": "p02", 
            "confidence": 1.7296531806812867e-15, 
            "word": "בה", 
            "gold_class": 0, 
            "predicted": "P"
        }, 
        {
            "lang": 0, 
            "gold_pos": "c", 
            "confidence": 6.6936484595622803e-11, 
            "word": "אלא", 
            "gold_class": 0, 
            "predicted": "a"
        }, 
        {
            "lang": 0, 
            "gold_pos": "n01", 
            "confidence": 4.8682043347598306e-16, 
            "word": "חמשה", 
            "gold_class": 0, 
            "predicted": "V01"
        }, 
        {
            "lang": 0, 
            "gold_pos": "", 
            "confidence": 4.010276942328017e-13, 
            "word": "והאמר", 
            "gold_class": 0, 
            "predicted": "a"
        }, 
        {
            "lang": 1, 
            "gold_pos": "", 
            "confidence": 0.0, 
            "word": "רבא", 
            "gold_class": 0, 
            "predicted": "*BOS*"
        }, 
        {
            "lang": 0, 
            "gold_pos": "", 
            "confidence": 9.7166776628549451e-09, 
            "word": "כל", 
            "gold_class": 0, 
            "predicted": "a"
        }, 
        {
            "lang": 0, 
            "gold_pos": "", 
            "confidence": 5.9430364815447887e-07, 
            "word": "דבר", 
            "gold_class": 0, 
            "predicted": "N01"
        }, 
        {
            "lang": 0, 
            "gold_pos": "", 
            "confidence": 1.8682379080785725e-16, 
            "word": "שבמדה", 
            "gold_class": 0, 
            "predicted": "V01"
        }, 
        {
            "lang": 0, 
            "gold_pos": "", 
            "confidence": 3.2765230776502334e-12, 
            "word": "ושבמשקל", 
            "gold_class": 0, 
            "predicted": "V01"
        }, 
        {
            "lang": 0, 
            "gold_pos": "", 
            "confidence": 1.1626455771431672e-05, 
            "word": "ושבמנין", 
            "gold_class": 0, 
            "predicted": "N03"
        }, 
        {
            "lang": 0, 
            "gold_pos": "", 
            "confidence": 1.4371150543210816e-11, 
            "word": "אפילו", 
            "gold_class": 0, 
            "predicted": "V01"
        }, 
        {
            "lang": 0, 
            "gold_pos": "", 
            "confidence": 3.0795736480588957e-09, 
            "word": "פחות", 
            "gold_class": 0, 
            "predicted": "V01"
        }, 
        {
            "lang": 1, 
            "gold_pos": "", 
            "confidence": 0.0, 
            "word": "מכדי", 
            "gold_class": 0, 
            "predicted": "*BOS*"
        }, 
        {
            "lang": 0, 
            "gold_pos": "", 
            "confidence": 6.4977995720125436e-15, 
            "word": "אונאה", 
            "gold_class": 0, 
            "predicted": "V01"
        }, 
        {
            "lang": 0, 
            "gold_pos": "", 
            "confidence": 2.3286927205455768e-08, 
            "word": "חוזר", 
            "gold_class": 0, 
            "predicted": "V01"
        }, 
        {
            "lang": 0, 
            "gold_pos": "", 
            "confidence": 1.0289238711314137e-11, 
            "word": "אלא", 
            "gold_class": 0, 
            "predicted": "c"
        }, 
        {
            "lang": 1, 
            "gold_pos": "", 
            "confidence": 0.0, 
            "word": "דאמר", 
            "gold_class": 0, 
            "predicted": "*BOS*"
        }, 
        {
            "lang": 1, 
            "gold_pos": "", 
            "confidence": 0.0, 
            "word": "איהו", 
            "gold_class": 0, 
            "predicted": "*BOS*"
        }, 
        {
            "lang": 1, 
            "gold_pos": "V01", 
            "confidence": 0.0, 
            "word": "שדאי", 
            "gold_class": 1, 
            "predicted": "*BOS*"
        }, 
        {
            "lang": 0, 
            "gold_pos": "p02", 
            "confidence": 8.6752664249269248e-15, 
            "word": "בה", 
            "gold_class": 0, 
            "predicted": "p02"
        }, 
        {
            "lang": 1, 
            "gold_pos": "V04", 
            "confidence": 3.50525303708178e-09, 
            "word": "כדאבעי", 
            "gold_class": 1, 
            "predicted": "V04"
        }, 
        {
            "lang": 0, 
            "gold_pos": "p02", 
            "confidence": 1.1497559012575457e-14, 
            "word": "לה", 
            "gold_class": 0, 
            "predicted": "p02"
        }, 
        {
            "lang": 1, 
            "gold_pos": "V05", 
            "confidence": 1.5255411656832401e-07, 
            "word": "ואיגלאי", 
            "gold_class": 1, 
            "predicted": "N05"
        }, 
        {
            "lang": 1, 
            "gold_pos": "N02", 
            "confidence": 0.0, 
            "word": "מילתא", 
            "gold_class": 1, 
            "predicted": "*BOS*"
        }, 
        {
            "lang": 1, 
            "gold_pos": "a", 
            "confidence": 0.0, 
            "word": "דלא", 
            "gold_class": 1, 
            "predicted": "*BOS*"
        }, 
        {
            "lang": 1, 
            "gold_pos": "V01", 
            "confidence": 0.0, 
            "word": "שדא", 
            "gold_class": 1, 
            "predicted": "*BOS*"
        }, 
        {
            "lang": 0, 
            "gold_pos": "p02", 
            "confidence": 1.1977265031107742e-12, 
            "word": "בה", 
            "gold_class": 0, 
            "predicted": "p01"
        }, 
        {
            "lang": 1, 
            "gold_pos": "V04", 
            "confidence": 4.9049061946135849e-10, 
            "word": "כדאבעי", 
            "gold_class": 1, 
            "predicted": "V03"
        }, 
        {
            "lang": 0, 
            "gold_pos": "p02", 
            "confidence": 1.9275062298820573e-15, 
            "word": "לה", 
            "gold_class": 0, 
            "predicted": "p02"
        }, 
        {
            "lang": 0, 
            "gold_pos": "", 
            "confidence": 9.4847287112669126e-16, 
            "word": "יש", 
            "gold_class": 0, 
            "predicted": "V01"
        }, 
        {
            "lang": 0, 
            "gold_pos": "", 
            "confidence": 1.3472422010809388e-14, 
            "word": "להם", 
            "gold_class": 0, 
            "predicted": "p01"
        }, 
        {
            "lang": 0, 
            "gold_pos": "", 
            "confidence": 6.1190032113195152e-13, 
            "word": "אונאה", 
            "gold_class": 0, 
            "predicted": "V01"
        }, 
        {
            "lang": 0, 
            "gold_pos": "c", 
            "confidence": 1.9745857465803795e-10, 
            "word": "או", 
            "gold_class": 0, 
            "predicted": "a"
        }, 
        {
            "lang": 0, 
            "gold_pos": "", 
            "confidence": 1.1109455546368707e-10, 
            "word": "אין", 
            "gold_class": 0, 
            "predicted": "c"
        }, 
        {
            "lang": 0, 
            "gold_pos": "p01", 
            "confidence": 6.3776268578653377e-13, 
            "word": "להם", 
            "gold_class": 0, 
            "predicted": "p01"
        }, 
        {
            "lang": 0, 
            "gold_pos": "", 
            "confidence": 2.124050571154655e-12, 
            "word": "אונאה", 
            "gold_class": 0, 
            "predicted": "N02"
        }, 
        {
            "lang": 1, 
            "gold_pos": "", 
            "confidence": 0.0, 
            "word": "כמאן", 
            "gold_class": 0, 
            "predicted": "*BOS*"
        }, 
        {
            "lang": 1, 
            "gold_pos": "", 
            "confidence": 0.0, 
            "word": "דשדי", 
            "gold_class": 0, 
            "predicted": "*BOS*"
        }, 
        {
            "lang": 1, 
            "gold_pos": "N02", 
            "confidence": 0.0, 
            "word": "בכדא", 
            "gold_class": 1, 
            "predicted": "*BOS*"
        }, 
        {
            "lang": 1, 
            "gold_pos": "", 
            "confidence": 0.0, 
            "word": "דמיין", 
            "gold_class": 0, 
            "predicted": "*BOS*"
        }, 
        {
            "lang": 0, 
            "gold_pos": "", 
            "confidence": 1.5365486829666303e-15, 
            "word": "ויש", 
            "gold_class": 0, 
            "predicted": "V01"
        }, 
        {
            "lang": 0, 
            "gold_pos": "", 
            "confidence": 1.4081798438783106e-14, 
            "word": "להם", 
            "gold_class": 0, 
            "predicted": "p01"
        }, 
        {
            "lang": 0, 
            "gold_pos": "", 
            "confidence": 1.7952618610056694e-12, 
            "word": "אונאה", 
            "gold_class": 0, 
            "predicted": "N02"
        }, 
        {
            "lang": 0, 
            "gold_pos": "c", 
            "confidence": 2.4640565017409244e-09, 
            "word": "או", 
            "gold_class": 0, 
            "predicted": "a"
        }, 
        {
            "lang": 1, 
            "gold_pos": "", 
            "confidence": 0.0, 
            "word": "דלמא", 
            "gold_class": 0, 
            "predicted": "*BOS*"
        }, 
        {
            "lang": 1, 
            "gold_pos": "", 
            "confidence": 8.390844210079657e-13, 
            "word": "בטלינהו", 
            "gold_class": 0, 
            "predicted": "V01"
        }, 
        {
            "lang": 1, 
            "gold_pos": "", 
            "confidence": 0.0, 
            "word": "אגב", 
            "gold_class": 0, 
            "predicted": "*BOS*"
        }, 
        {
            "lang": 1, 
            "gold_pos": "N02", 
            "confidence": 0.0, 
            "word": "ארעא", 
            "gold_class": 1, 
            "predicted": "*BOS*"
        }, 
        {
            "lang": 0, 
            "gold_pos": "", 
            "confidence": 3.5611921264521778e-08, 
            "word": "נשבעין", 
            "gold_class": 0, 
            "predicted": "V04"
        }, 
        {
            "lang": 0, 
            "gold_pos": "", 
            "confidence": 7.2408265829400856e-17, 
            "word": "עליהן", 
            "gold_class": 0, 
            "predicted": "p02"
        }, 
        {
            "lang": 0, 
            "gold_pos": "c", 
            "confidence": 7.9785188645109336e-11, 
            "word": "או", 
            "gold_class": 0, 
            "predicted": "a"
        }, 
        {
            "lang": 0, 
            "gold_pos": "", 
            "confidence": 8.1223133849476932e-17, 
            "word": "אין", 
            "gold_class": 0, 
            "predicted": "P"
        }, 
        {
            "lang": 0, 
            "gold_pos": "", 
            "confidence": 5.949639710233227e-10, 
            "word": "נשבעין", 
            "gold_class": 0, 
            "predicted": "V01"
        }, 
        {
            "lang": 0, 
            "gold_pos": "", 
            "confidence": 1.6702581805641815e-15, 
            "word": "עליהן", 
            "gold_class": 0, 
            "predicted": "p02"
        }, 
        {
            "lang": 1, 
            "gold_pos": "", 
            "confidence": 0.0, 
            "word": "כמאן", 
            "gold_class": 0, 
            "predicted": "*BOS*"
        }, 
        {
            "lang": 1, 
            "gold_pos": "", 
            "confidence": 5.2447145514380167e-06, 
            "word": "דשדיין", 
            "gold_class": 0, 
            "predicted": "V01"
        }, 
        {
            "lang": 1, 
            "gold_pos": "", 
            "confidence": 0.0, 
            "word": "בכדא", 
            "gold_class": 0, 
            "predicted": "*BOS*"
        }, 
        {
            "lang": 1, 
            "gold_pos": "", 
            "confidence": 0.0, 
            "word": "דמיין", 
            "gold_class": 0, 
            "predicted": "*BOS*"
        }, 
        {
            "lang": 0, 
            "gold_pos": "", 
            "confidence": 4.3585748349755902e-11, 
            "word": "ונשבעין", 
            "gold_class": 0, 
            "predicted": "V01"
        }, 
        {
            "lang": 0, 
            "gold_pos": "", 
            "confidence": 1.8353969384910868e-17, 
            "word": "עליהן", 
            "gold_class": 0, 
            "predicted": "p02"
        }, 
        {
            "lang": 0, 
            "gold_pos": "", 
            "confidence": 1.9709490787717472e-10, 
            "word": "או", 
            "gold_class": 0, 
            "predicted": "a"
        }, 
        {
            "lang": 1, 
            "gold_pos": "", 
            "confidence": 0.0, 
            "word": "דלמא", 
            "gold_class": 0, 
            "predicted": "*BOS*"
        }, 
        {
            "lang": 1, 
            "gold_pos": "", 
            "confidence": 3.0265588327378253e-14, 
            "word": "בטלינהו", 
            "gold_class": 0, 
            "predicted": "V01"
        }, 
        {
            "lang": 1, 
            "gold_pos": "", 
            "confidence": 0.0, 
            "word": "אגב", 
            "gold_class": 0, 
            "predicted": "*BOS*"
        }, 
        {
            "lang": 1, 
            "gold_pos": "", 
            "confidence": 0.0, 
            "word": "ארעא", 
            "gold_class": 0, 
            "predicted": "*BOS*"
        }, 
        {
            "lang": 0, 
            "gold_pos": "", 
            "confidence": 1.8108330755933085e-17, 
            "word": "ואין", 
            "gold_class": 0, 
            "predicted": "P"
        }, 
        {
            "lang": 0, 
            "gold_pos": "", 
            "confidence": 6.6359749438795342e-10, 
            "word": "נשבעין", 
            "gold_class": 0, 
            "predicted": "V01"
        }, 
        {
            "lang": 0, 
            "gold_pos": "", 
            "confidence": 3.8482784313975059e-16, 
            "word": "עליהן", 
            "gold_class": 0, 
            "predicted": "p02"
        }, 
        {
            "lang": 0, 
            "gold_pos": "", 
            "confidence": 4.3830187618321234e-10, 
            "word": "עומר", 
            "gold_class": 0, 
            "predicted": "V02"
        }, 
        {
            "lang": 0, 
            "gold_pos": "", 
            "confidence": 4.9849571534152442e-11, 
            "word": "מתירן", 
            "gold_class": 0, 
            "predicted": "p02"
        }, 
        {
            "lang": 0, 
            "gold_pos": "", 
            "confidence": 6.2750277910475404e-10, 
            "word": "או", 
            "gold_class": 0, 
            "predicted": "a"
        }, 
        {
            "lang": 0, 
            "gold_pos": "", 
            "confidence": 4.9779285347487779e-17, 
            "word": "אין", 
            "gold_class": 0, 
            "predicted": "P"
        }, 
        {
            "lang": 0, 
            "gold_pos": "", 
            "confidence": 1.3251256671124181e-06, 
            "word": "עומר", 
            "gold_class": 0, 
            "predicted": "V02"
        }, 
        {
            "lang": 0, 
            "gold_pos": "", 
            "confidence": 5.7652670194287442e-08, 
            "word": "מתירן", 
            "gold_class": 0, 
            "predicted": "p02"
        }, 
        {
            "lang": 1, 
            "gold_pos": "a", 
            "confidence": 0.0, 
            "word": "היכי", 
            "gold_class": 1, 
            "predicted": "*BOS*"
        }, 
        {
            "lang": 1, 
            "gold_pos": "V01", 
            "confidence": 0.0, 
            "word": "דמי", 
            "gold_class": 1, 
            "predicted": "*BOS*"
        }, 
        {
            "lang": 1, 
            "gold_pos": "c", 
            "confidence": 0.0, 
            "word": "אי", 
            "gold_class": 1, 
            "predicted": "*BOS*"
        }, 
        {
            "lang": 1, 
            "gold_pos": "V03", 
            "confidence": 2.2060674073053025e-11, 
            "word": "דאשרוש", 
            "gold_class": 1, 
            "predicted": "V01"
        }, 
        {
            "lang": 1, 
            "gold_pos": "V01", 
            "confidence": 0.0, 
            "word": "תנינא", 
            "gold_class": 1, 
            "predicted": "*BOS*"
        }, 
        {
            "lang": 1, 
            "gold_pos": "c", 
            "confidence": 0.0, 
            "word": "אי", 
            "gold_class": 1, 
            "predicted": "*BOS*"
        }, 
        {
            "lang": 1, 
            "gold_pos": "a", 
            "confidence": 0.0, 
            "word": "דלא", 
            "gold_class": 1, 
            "predicted": "*BOS*"
        }, 
        {
            "lang": 1, 
            "gold_pos": "V03", 
            "confidence": 3.8175695351385503e-17, 
            "word": "אשרוש", 
            "gold_class": 1, 
            "predicted": "V01"
        }, 
        {
            "lang": 1, 
            "gold_pos": "V01", 
            "confidence": 0.0, 
            "word": "תנינא", 
            "gold_class": 1, 
            "predicted": "*BOS*"
        }, 
        {
            "lang": 1, 
            "gold_pos": "", 
            "confidence": 0.0, 
            "word": "דתנן", 
            "gold_class": 0, 
            "predicted": "*BOS*"
        }, 
        {
            "lang": 0, 
            "gold_pos": "", 
            "confidence": 2.1262988393560166e-15, 
            "word": "אם", 
            "gold_class": 0, 
            "predicted": "a"
        }, 
        {
            "lang": 0, 
            "gold_pos": "", 
            "confidence": 5.3268781082894349e-06, 
            "word": "השרישו", 
            "gold_class": 0, 
            "predicted": "a"
        }, 
        {
            "lang": 0, 
            "gold_pos": "", 
            "confidence": 5.3600937283846671e-08, 
            "word": "קודם", 
            "gold_class": 0, 
            "predicted": "c"
        }, 
        {
            "lang": 0, 
            "gold_pos": "", 
            "confidence": 7.6013074979900337e-12, 
            "word": "לעומר", 
            "gold_class": 0, 
            "predicted": "V02"
        }, 
        {
            "lang": 0, 
            "gold_pos": "", 
            "confidence": 2.7871808899681052e-10, 
            "word": "עומר", 
            "gold_class": 0, 
            "predicted": "V02"
        }, 
        {
            "lang": 0, 
            "gold_pos": "", 
            "confidence": 6.376501062893096e-06, 
            "word": "מתירן", 
            "gold_class": 0, 
            "predicted": "p02"
        }, 
        {
            "lang": 0, 
            "gold_pos": "", 
            "confidence": 1.096124408933793e-17, 
            "word": "ואם", 
            "gold_class": 0, 
            "predicted": "a"
        }, 
        {
            "lang": 1, 
            "gold_pos": "", 
            "confidence": 0.0, 
            "word": "לאו", 
            "gold_class": 0, 
            "predicted": "*BOS*"
        }, 
        {
            "lang": 0, 
            "gold_pos": "", 
            "confidence": 3.8217213183772178e-08, 
            "word": "אסורין", 
            "gold_class": 0, 
            "predicted": "N02"
        }, 
        {
            "lang": 0, 
            "gold_pos": "", 
            "confidence": 1.7528771401148996e-10, 
            "word": "עד", 
            "gold_class": 0, 
            "predicted": "n01"
        }, 
        {
            "lang": 0, 
            "gold_pos": "", 
            "confidence": 1.0126913099383387e-15, 
            "word": "שיבא", 
            "gold_class": 0, 
            "predicted": "V01"
        }, 
        {
            "lang": 0, 
            "gold_pos": "", 
            "confidence": 7.97795673245049e-10, 
            "word": "עומר", 
            "gold_class": 0, 
            "predicted": "V01"
        }, 
        {
            "lang": 0, 
            "gold_pos": "", 
            "confidence": 1.1635718315943468e-13, 
            "word": "הבא", 
            "gold_class": 0, 
            "predicted": "V01"
        }, 
        {
            "lang": 0, 
            "gold_pos": "a", 
            "confidence": 2.4638147077491456e-14, 
            "word": "לא", 
            "gold_class": 0, 
            "predicted": "a"
        }, 
        {
            "lang": 1, 
            "gold_pos": "A01", 
            "confidence": 0.0, 
            "word": "צריכא", 
            "gold_class": 1, 
            "predicted": "*BOS*"
        }, 
        {
            "lang": 1, 
            "gold_pos": "V01", 
            "confidence": 3.9945370047147123e-10, 
            "word": "דחצדינהו", 
            "gold_class": 1, 
            "predicted": "V01"
        }, 
        {
            "lang": 1, 
            "gold_pos": "V01", 
            "confidence": 4.4714433013099187e-15, 
            "word": "וזרעינהו", 
            "gold_class": 1, 
            "predicted": "V01"
        }, 
        {
            "lang": 0, 
            "gold_pos": "", 
            "confidence": 2.9923932038365361e-07, 
            "word": "קודם", 
            "gold_class": 0, 
            "predicted": "V03"
        }, 
        {
            "lang": 0, 
            "gold_pos": "", 
            "confidence": 4.9910796557614598e-08, 
            "word": "לעומר", 
            "gold_class": 0, 
            "predicted": "N02"
        }, 
        {
            "lang": 1, 
            "gold_pos": "V01", 
            "confidence": 0.0, 
            "word": "ואתא", 
            "gold_class": 1, 
            "predicted": "*BOS*"
        }, 
        {
            "lang": 1, 
            "gold_pos": "p02", 
            "confidence": 7.7603567199051048e-19, 
            "word": "ליה", 
            "gold_class": 1, 
            "predicted": "*BOS*"
        }, 
        {
            "lang": 0, 
            "gold_pos": "", 
            "confidence": 2.0299908157634681e-08, 
            "word": "עומר", 
            "gold_class": 0, 
            "predicted": "V02"
        }, 
        {
            "lang": 1, 
            "gold_pos": "V01", 
            "confidence": 0.0, 
            "word": "וחליף", 
            "gold_class": 1, 
            "predicted": "*BOS*"
        }, 
        {
            "lang": 1, 
            "gold_pos": "", 
            "confidence": 1.5033766379085445e-08, 
            "word": "עילוייהו", 
            "gold_class": 0, 
            "predicted": "p02"
        }, 
        {
            "lang": 0, 
            "gold_pos": "", 
            "confidence": 1.8853709879210953e-13, 
            "word": "ולא", 
            "gold_class": 0, 
            "predicted": "a"
        }, 
        {
            "lang": 1, 
            "gold_pos": "", 
            "confidence": 9.1769775144878739e-13, 
            "word": "אשרוש", 
            "gold_class": 0, 
            "predicted": "V03"
        }, 
        {
            "lang": 0, 
            "gold_pos": "", 
            "confidence": 1.2217630057142949e-06, 
            "word": "קודם", 
            "gold_class": 0, 
            "predicted": "V03"
        }, 
        {
            "lang": 0, 
            "gold_pos": "", 
            "confidence": 2.8204991112263375e-08, 
            "word": "לעומר", 
            "gold_class": 0, 
            "predicted": "V03"
        }
    ]
}