{
    "file": "Bava Metzia_58a", 
    "words": [
        {
            "lang": 0, 
            "gold_pos": "", 
            "confidence": 2.6352089200156953e-07, 
            "word": "נשבעין", 
            "gold_class": 0, 
            "predicted": "n03"
        }, 
        {
            "lang": 0, 
            "gold_pos": "", 
            "confidence": 0.0027264736871374022, 
            "word": "לגזברין", 
            "gold_class": 0, 
            "predicted": "V09"
        }, 
        {
            "lang": 0, 
            "gold_pos": "", 
            "confidence": 3.2121580795949135e-05, 
            "word": "ואם", 
            "gold_class": 0, 
            "predicted": "c"
        }, 
        {
            "lang": 0, 
            "gold_pos": "", 
            "confidence": 4.5133522714462985e-05, 
            "word": "לאו", 
            "gold_class": 0, 
            "predicted": "p01"
        }, 
        {
            "lang": 0, 
            "gold_pos": "", 
            "confidence": 4.8645056176123183e-07, 
            "word": "נשבעין", 
            "gold_class": 0, 
            "predicted": "V01"
        }, 
        {
            "lang": 0, 
            "gold_pos": "", 
            "confidence": 2.706390071960995e-06, 
            "word": "לבני", 
            "gold_class": 0, 
            "predicted": "P"
        }, 
        {
            "lang": 0, 
            "gold_pos": "", 
            "confidence": 2.6144984857947094e-08, 
            "word": "העיר", 
            "gold_class": 0, 
            "predicted": "V01"
        }, 
        {
            "lang": 0, 
            "gold_pos": "", 
            "confidence": 7.9014385888584747e-06, 
            "word": "ובני", 
            "gold_class": 0, 
            "predicted": "N05"
        }, 
        {
            "lang": 0, 
            "gold_pos": "", 
            "confidence": 1.594861808310185e-08, 
            "word": "העיר", 
            "gold_class": 0, 
            "predicted": "V01"
        }, 
        {
            "lang": 0, 
            "gold_pos": "", 
            "confidence": 1.3383167334068496e-05, 
            "word": "שוקלין", 
            "gold_class": 0, 
            "predicted": "V02"
        }, 
        {
            "lang": 0, 
            "gold_pos": "", 
            "confidence": 2.1446109960549436e-05, 
            "word": "אחרים", 
            "gold_class": 0, 
            "predicted": "V01"
        }, 
        {
            "lang": 0, 
            "gold_pos": "", 
            "confidence": 6.3550448370109961e-05, 
            "word": "תחתיהן", 
            "gold_class": 0, 
            "predicted": "N02"
        }, 
        {
            "lang": 0, 
            "gold_pos": "", 
            "confidence": 0.00053033921026125069, 
            "word": "נמצאו", 
            "gold_class": 0, 
            "predicted": "N05"
        }, 
        {
            "lang": 0, 
            "gold_pos": "", 
            "confidence": 5.3637780963408148e-05, 
            "word": "או", 
            "gold_class": 0, 
            "predicted": "P"
        }, 
        {
            "lang": 0, 
            "gold_pos": "", 
            "confidence": 1.4177049749456518e-06, 
            "word": "שהחזירום", 
            "gold_class": 0, 
            "predicted": "V01"
        }, 
        {
            "lang": 0, 
            "gold_pos": "", 
            "confidence": 3.577525379293343e-07, 
            "word": "הגנבים", 
            "gold_class": 0, 
            "predicted": "V01"
        }, 
        {
            "lang": 0, 
            "gold_pos": "", 
            "confidence": 0.0019948090883017944, 
            "word": "אלו", 
            "gold_class": 0, 
            "predicted": "p01"
        }, 
        {
            "lang": 0, 
            "gold_pos": "", 
            "confidence": 8.5966667016695956e-05, 
            "word": "ואלו", 
            "gold_class": 0, 
            "predicted": "c"
        }, 
        {
            "lang": 0, 
            "gold_pos": "", 
            "confidence": 4.6820124422411352e-09, 
            "word": "שקלים", 
            "gold_class": 0, 
            "predicted": "V01"
        }, 
        {
            "lang": 0, 
            "gold_pos": "", 
            "confidence": 1.0546527721500833e-07, 
            "word": "הם", 
            "gold_class": 0, 
            "predicted": "P"
        }, 
        {
            "lang": 0, 
            "gold_pos": "", 
            "confidence": 4.9781787935790094e-07, 
            "word": "ואין", 
            "gold_class": 0, 
            "predicted": "V01"
        }, 
        {
            "lang": 0, 
            "gold_pos": "", 
            "confidence": 1.6224507727878165e-09, 
            "word": "עולין", 
            "gold_class": 0, 
            "predicted": "V02"
        }, 
        {
            "lang": 0, 
            "gold_pos": "", 
            "confidence": 0.00023813424819100194, 
            "word": "להם", 
            "gold_class": 0, 
            "predicted": "P"
        }, 
        {
            "lang": 0, 
            "gold_pos": "", 
            "confidence": 4.3875213305252053e-06, 
            "word": "לשנה", 
            "gold_class": 0, 
            "predicted": "N02"
        }, 
        {
            "lang": 0, 
            "gold_pos": "", 
            "confidence": 1.2054982095582049e-05, 
            "word": "הבאה", 
            "gold_class": 0, 
            "predicted": "N02"
        }, 
        {
            "lang": 0, 
            "gold_pos": "", 
            "confidence": 3.8394218205960865e-10, 
            "word": "אמר", 
            "gold_class": 0, 
            "predicted": "V01"
        }, 
        {
            "lang": 1, 
            "gold_pos": "", 
            "confidence": 0.0, 
            "word": "שמואל", 
            "gold_class": 0, 
            "predicted": "PN"
        }, 
        {
            "lang": 1, 
            "gold_pos": "", 
            "confidence": 0.0, 
            "word": "הכא", 
            "gold_class": 0, 
            "predicted": "a"
        }, 
        {
            "lang": 1, 
            "gold_pos": "", 
            "confidence": 7.9496812331424319e-08, 
            "word": "בנושא", 
            "gold_class": 0, 
            "predicted": "N02"
        }, 
        {
            "lang": 0, 
            "gold_pos": "", 
            "confidence": 5.5536020290895779e-07, 
            "word": "שכר", 
            "gold_class": 0, 
            "predicted": "V01"
        }, 
        {
            "lang": 1, 
            "gold_pos": "", 
            "confidence": 0.0, 
            "word": "עסקינן", 
            "gold_class": 0, 
            "predicted": "V01"
        }, 
        {
            "lang": 0, 
            "gold_pos": "", 
            "confidence": 2.4195147847517698e-06, 
            "word": "ונשבעין", 
            "gold_class": 0, 
            "predicted": "N03"
        }, 
        {
            "lang": 1, 
            "gold_pos": "", 
            "confidence": 9.044520192972148e-09, 
            "word": "ליטול", 
            "gold_class": 0, 
            "predicted": "V01"
        }, 
        {
            "lang": 0, 
            "gold_pos": "", 
            "confidence": 3.3687226284573644e-05, 
            "word": "שכרן", 
            "gold_class": 0, 
            "predicted": "N02"
        }, 
        {
            "lang": 1, 
            "gold_pos": "c", 
            "confidence": 0.0, 
            "word": "אי", 
            "gold_class": 1, 
            "predicted": "c"
        }, 
        {
            "lang": 1, 
            "gold_pos": "a", 
            "confidence": 0.0, 
            "word": "הכי", 
            "gold_class": 1, 
            "predicted": "a"
        }, 
        {
            "lang": 0, 
            "gold_pos": "", 
            "confidence": 1.1555748402733308e-06, 
            "word": "נשבעין", 
            "gold_class": 0, 
            "predicted": "V02"
        }, 
        {
            "lang": 0, 
            "gold_pos": "", 
            "confidence": 2.1376318477173171e-05, 
            "word": "לגזברין", 
            "gold_class": 0, 
            "predicted": "V04"
        }, 
        {
            "lang": 0, 
            "gold_pos": "", 
            "confidence": 4.6375544208315641e-06, 
            "word": "לבני", 
            "gold_class": 0, 
            "predicted": "N05"
        }, 
        {
            "lang": 0, 
            "gold_pos": "", 
            "confidence": 1.9740090558508622e-07, 
            "word": "העיר", 
            "gold_class": 0, 
            "predicted": "V01"
        }, 
        {
            "lang": 1, 
            "gold_pos": "V04", 
            "confidence": 0.0, 
            "word": "מבעי", 
            "gold_class": 1, 
            "predicted": "V04"
        }, 
        {
            "lang": 1, 
            "gold_pos": "p02", 
            "confidence": 3.4398926787951299e-06, 
            "word": "ליה", 
            "gold_class": 1, 
            "predicted": "p02"
        }, 
        {
            "lang": 0, 
            "gold_pos": "", 
            "confidence": 1.3075375667310318e-09, 
            "word": "אמר", 
            "gold_class": 0, 
            "predicted": "V01"
        }, 
        {
            "lang": 0, 
            "gold_pos": "", 
            "confidence": 3.0696800555504021e-05, 
            "word": "רבה", 
            "gold_class": 0, 
            "predicted": "N02"
        }, 
        {
            "lang": 0, 
            "gold_pos": "", 
            "confidence": 4.2612052975382268e-06, 
            "word": "נשבעין", 
            "gold_class": 0, 
            "predicted": "V09"
        }, 
        {
            "lang": 0, 
            "gold_pos": "", 
            "confidence": 5.8596097790332551e-06, 
            "word": "לבני", 
            "gold_class": 0, 
            "predicted": "P"
        }, 
        {
            "lang": 0, 
            "gold_pos": "", 
            "confidence": 4.6053993658272811e-08, 
            "word": "העיר", 
            "gold_class": 0, 
            "predicted": "V01"
        }, 
        {
            "lang": 0, 
            "gold_pos": "", 
            "confidence": 5.2581179849604784e-08, 
            "word": "במעמד", 
            "gold_class": 0, 
            "predicted": "V01"
        }, 
        {
            "lang": 0, 
            "gold_pos": "", 
            "confidence": 5.046483804629431e-06, 
            "word": "גזברין", 
            "gold_class": 0, 
            "predicted": "V02"
        }, 
        {
            "lang": 0, 
            "gold_pos": "c", 
            "confidence": 1.5729786449077858e-06, 
            "word": "כי", 
            "gold_class": 0, 
            "predicted": "c"
        }, 
        {
            "lang": 1, 
            "gold_pos": "c", 
            "confidence": 0.0, 
            "word": "היכי", 
            "gold_class": 1, 
            "predicted": "c"
        }, 
        {
            "lang": 1, 
            "gold_pos": "a", 
            "confidence": 0.0, 
            "word": "דלא", 
            "gold_class": 1, 
            "predicted": "a"
        }, 
        {
            "lang": 1, 
            "gold_pos": "V01", 
            "confidence": 0.0, 
            "word": "נחשדינהו", 
            "gold_class": 1, 
            "predicted": "V01"
        }, 
        {
            "lang": 1, 
            "gold_pos": "", 
            "confidence": 0.0, 
            "word": "ואי", 
            "gold_class": 0, 
            "predicted": "c"
        }, 
        {
            "lang": 1, 
            "gold_pos": "", 
            "confidence": 0.0, 
            "word": "נמי", 
            "gold_class": 0, 
            "predicted": "a"
        }, 
        {
            "lang": 0, 
            "gold_pos": "", 
            "confidence": 3.1063335308002275e-09, 
            "word": "כי", 
            "gold_class": 0, 
            "predicted": "c"
        }, 
        {
            "lang": 1, 
            "gold_pos": "", 
            "confidence": 0.0, 
            "word": "היכי", 
            "gold_class": 0, 
            "predicted": "a"
        }, 
        {
            "lang": 1, 
            "gold_pos": "", 
            "confidence": 0.0, 
            "word": "דלא", 
            "gold_class": 0, 
            "predicted": "a"
        }, 
        {
            "lang": 0, 
            "gold_pos": "", 
            "confidence": 2.8426364944053524e-10, 
            "word": "לקרו", 
            "gold_class": 0, 
            "predicted": "V01"
        }, 
        {
            "lang": 1, 
            "gold_pos": "", 
            "confidence": 3.2832892790723966e-05, 
            "word": "להו", 
            "gold_class": 0, 
            "predicted": "p01"
        }, 
        {
            "lang": 0, 
            "gold_pos": "", 
            "confidence": 1.0891418792319145e-05, 
            "word": "פושעים", 
            "gold_class": 0, 
            "predicted": "N02"
        }, 
        {
            "lang": 1, 
            "gold_pos": "I", 
            "confidence": 0.0, 
            "word": "והא", 
            "gold_class": 1, 
            "predicted": "I"
        }, 
        {
            "lang": 0, 
            "gold_pos": "", 
            "confidence": 9.706665981628249e-09, 
            "word": "נגנבו", 
            "gold_class": 0, 
            "predicted": "V04"
        }, 
        {
            "lang": 0, 
            "gold_pos": "", 
            "confidence": 1.649375753298599e-08, 
            "word": "או", 
            "gold_class": 0, 
            "predicted": "c"
        }, 
        {
            "lang": 0, 
            "gold_pos": "", 
            "confidence": 1.1966984493847735e-06, 
            "word": "שאבדו", 
            "gold_class": 0, 
            "predicted": "N02"
        }, 
        {
            "lang": 1, 
            "gold_pos": "V01", 
            "confidence": 0.0, 
            "word": "קתני", 
            "gold_class": 1, 
            "predicted": "V01"
        }, 
        {
            "lang": 0, 
            "gold_pos": "", 
            "confidence": 2.8963364738726627e-06, 
            "word": "ושומר", 
            "gold_class": 0, 
            "predicted": "PN"
        }, 
        {
            "lang": 0, 
            "gold_pos": "", 
            "confidence": 2.6452919831444066e-07, 
            "word": "שכר", 
            "gold_class": 0, 
            "predicted": "V01"
        }, 
        {
            "lang": 0, 
            "gold_pos": "", 
            "confidence": 4.1720100074281088e-08, 
            "word": "בגניבה", 
            "gold_class": 0, 
            "predicted": "N05"
        }, 
        {
            "lang": 0, 
            "gold_pos": "", 
            "confidence": 1.5507928148922776e-05, 
            "word": "ואבידה", 
            "gold_class": 0, 
            "predicted": "N02"
        }, 
        {
            "lang": 1, 
            "gold_pos": "V02", 
            "confidence": 0.0, 
            "word": "חיובי", 
            "gold_class": 1, 
            "predicted": "V02"
        }, 
        {
            "lang": 1, 
            "gold_pos": "V02", 
            "confidence": 0.0, 
            "word": "מיחייב", 
            "gold_class": 1, 
            "predicted": "V02"
        }, 
        {
            "lang": 1, 
            "gold_pos": "a", 
            "confidence": 0.0, 
            "word": "והכא", 
            "gold_class": 1, 
            "predicted": "a"
        }, 
        {
            "lang": 1, 
            "gold_pos": "", 
            "confidence": 0.0, 
            "word": "נמי", 
            "gold_class": 0, 
            "predicted": "a"
        }, 
        {
            "lang": 1, 
            "gold_pos": "V01", 
            "confidence": 0.0, 
            "word": "נהי", 
            "gold_class": 1, 
            "predicted": "V01"
        }, 
        {
            "lang": 1, 
            "gold_pos": "V02", 
            "confidence": 0.0, 
            "word": "דשלומי", 
            "gold_class": 1, 
            "predicted": "V02"
        }, 
        {
            "lang": 0, 
            "gold_pos": "a", 
            "confidence": 1.9241027645377619e-06, 
            "word": "לא", 
            "gold_class": 0, 
            "predicted": "a"
        }, 
        {
            "lang": 1, 
            "gold_pos": "V02", 
            "confidence": 0.0, 
            "word": "משלמי", 
            "gold_class": 1, 
            "predicted": "V02"
        }, 
        {
            "lang": 1, 
            "gold_pos": "", 
            "confidence": 0.0, 
            "word": "אגרייהו", 
            "gold_class": 0, 
            "predicted": "N02"
        }, 
        {
            "lang": 1, 
            "gold_pos": "a", 
            "confidence": 0.0, 
            "word": "מיהא", 
            "gold_class": 1, 
            "predicted": "a"
        }, 
        {
            "lang": 1, 
            "gold_pos": "V01", 
            "confidence": 0.0, 
            "word": "לפסיד", 
            "gold_class": 1, 
            "predicted": "V01"
        }, 
        {
            "lang": 0, 
            "gold_pos": "", 
            "confidence": 1.2630439588125062e-10, 
            "word": "אמר", 
            "gold_class": 0, 
            "predicted": "V01"
        }, 
        {
            "lang": 0, 
            "gold_pos": "", 
            "confidence": 1.176639179590462e-06, 
            "word": "רבה", 
            "gold_class": 0, 
            "predicted": "N02"
        }, 
        {
            "lang": 0, 
            "gold_pos": "", 
            "confidence": 1.3294346391686884e-06, 
            "word": "נגנבו", 
            "gold_class": 0, 
            "predicted": "V02"
        }, 
        {
            "lang": 0, 
            "gold_pos": "", 
            "confidence": 1.3509133349859526e-05, 
            "word": "בלסטים", 
            "gold_class": 0, 
            "predicted": "V08"
        }, 
        {
            "lang": 0, 
            "gold_pos": "", 
            "confidence": 0.00024818632700883512, 
            "word": "מזויין", 
            "gold_class": 0, 
            "predicted": "V03"
        }, 
        {
            "lang": 0, 
            "gold_pos": "", 
            "confidence": 6.3589785528740407e-07, 
            "word": "אבדו", 
            "gold_class": 0, 
            "predicted": "V03"
        }, 
        {
            "lang": 0, 
            "gold_pos": "", 
            "confidence": 3.4938797246054969e-07, 
            "word": "שטבעה", 
            "gold_class": 0, 
            "predicted": "V01"
        }, 
        {
            "lang": 0, 
            "gold_pos": "", 
            "confidence": 9.8400190300023001e-07, 
            "word": "ספינתו", 
            "gold_class": 0, 
            "predicted": "a"
        }, 
        {
            "lang": 0, 
            "gold_pos": "", 
            "confidence": 5.5325008674412447e-08, 
            "word": "בים", 
            "gold_class": 0, 
            "predicted": "N01"
        }, 
        {
            "lang": 0, 
            "gold_pos": "", 
            "confidence": 5.7710767621366924e-06, 
            "word": "רבי", 
            "gold_class": 0, 
            "predicted": "N01"
        }, 
        {
            "lang": 0, 
            "gold_pos": "", 
            "confidence": 9.5620262618396735e-09, 
            "word": "יוחנן", 
            "gold_class": 0, 
            "predicted": "N05"
        }, 
        {
            "lang": 0, 
            "gold_pos": "", 
            "confidence": 3.2461997164045335e-09, 
            "word": "אמר", 
            "gold_class": 0, 
            "predicted": "V01"
        }, 
        {
            "lang": 1, 
            "gold_pos": "", 
            "confidence": 0.0, 
            "word": "הא", 
            "gold_class": 0, 
            "predicted": "P"
        }, 
        {
            "lang": 1, 
            "gold_pos": "", 
            "confidence": 0.0, 
            "word": "מני", 
            "gold_class": 0, 
            "predicted": "P"
        }, 
        {
            "lang": 0, 
            "gold_pos": "", 
            "confidence": 6.3533664496241846e-09, 
            "word": "רבי", 
            "gold_class": 0, 
            "predicted": "N05"
        }, 
        {
            "lang": 0, 
            "gold_pos": "", 
            "confidence": 1.219940844487497e-07, 
            "word": "שמעון", 
            "gold_class": 0, 
            "predicted": "V01"
        }, 
        {
            "lang": 0, 
            "gold_pos": "", 
            "confidence": 6.1919933956085011e-09, 
            "word": "היא", 
            "gold_class": 0, 
            "predicted": "P"
        }, 
        {
            "lang": 1, 
            "gold_pos": "", 
            "confidence": 0.0, 
            "word": "דאמר", 
            "gold_class": 0, 
            "predicted": "V01"
        }, 
        {
            "lang": 0, 
            "gold_pos": "", 
            "confidence": 1.2854255919969772e-05, 
            "word": "קדשים", 
            "gold_class": 0, 
            "predicted": "V02"
        }, 
        {
            "lang": 1, 
            "gold_pos": "", 
            "confidence": 4.2471917145635081e-08, 
            "word": "שחייב", 
            "gold_class": 0, 
            "predicted": "V05"
        }, 
        {
            "lang": 0, 
            "gold_pos": "", 
            "confidence": 0.00892429701975209, 
            "word": "באחריותן", 
            "gold_class": 0, 
            "predicted": "p02"
        }, 
        {
            "lang": 0, 
            "gold_pos": "", 
            "confidence": 5.4082273607357072e-08, 
            "word": "יש", 
            "gold_class": 0, 
            "predicted": "V01"
        }, 
        {
            "lang": 0, 
            "gold_pos": "", 
            "confidence": 4.4104027315032177e-05, 
            "word": "להן", 
            "gold_class": 0, 
            "predicted": "p02"
        }, 
        {
            "lang": 1, 
            "gold_pos": "", 
            "confidence": 0.0012797072887375152, 
            "word": "אונאה", 
            "gold_class": 0, 
            "predicted": "N02"
        }, 
        {
            "lang": 0, 
            "gold_pos": "", 
            "confidence": 1.094885475785391e-06, 
            "word": "ונשבעין", 
            "gold_class": 0, 
            "predicted": "N03"
        }, 
        {
            "lang": 0, 
            "gold_pos": "", 
            "confidence": 2.9328565121557051e-05, 
            "word": "עליהם", 
            "gold_class": 0, 
            "predicted": "p02"
        }, 
        {
            "lang": 1, 
            "gold_pos": "", 
            "confidence": 0.0, 
            "word": "התינח", 
            "gold_class": 0, 
            "predicted": "V01"
        }, 
        {
            "lang": 0, 
            "gold_pos": "", 
            "confidence": 1.9879923899345748e-05, 
            "word": "עד", 
            "gold_class": 0, 
            "predicted": "p01"
        }, 
        {
            "lang": 0, 
            "gold_pos": "", 
            "confidence": 6.1381264459105628e-06, 
            "word": "שלא", 
            "gold_class": 0, 
            "predicted": "V01"
        }, 
        {
            "lang": 1, 
            "gold_pos": "", 
            "confidence": 4.1698986480463114e-06, 
            "word": "נתרמה", 
            "gold_class": 0, 
            "predicted": "V01"
        }, 
        {
            "lang": 0, 
            "gold_pos": "", 
            "confidence": 2.9505095656609871e-06, 
            "word": "התרומה", 
            "gold_class": 0, 
            "predicted": "V01"
        }, 
        {
            "lang": 0, 
            "gold_pos": "", 
            "confidence": 8.3886754550154603e-06, 
            "word": "משנתרמה", 
            "gold_class": 0, 
            "predicted": "V12"
        }, 
        {
            "lang": 0, 
            "gold_pos": "", 
            "confidence": 1.7844226460800868e-06, 
            "word": "התרומה", 
            "gold_class": 0, 
            "predicted": "V01"
        }, 
        {
            "lang": 0, 
            "gold_pos": "", 
            "confidence": 1.4495923307797596e-05, 
            "word": "קדשים", 
            "gold_class": 0, 
            "predicted": "V02"
        }, 
        {
            "lang": 0, 
            "gold_pos": "", 
            "confidence": 1.3535231875496356e-05, 
            "word": "שאינו", 
            "gold_class": 0, 
            "predicted": "P"
        }, 
        {
            "lang": 0, 
            "gold_pos": "", 
            "confidence": 2.1415701927931984e-08, 
            "word": "חייב", 
            "gold_class": 0, 
            "predicted": "V02"
        }, 
        {
            "lang": 0, 
            "gold_pos": "", 
            "confidence": 0.0016563143292800185, 
            "word": "באחריותן", 
            "gold_class": 0, 
            "predicted": "p02"
        }, 
        {
            "lang": 1, 
            "gold_pos": "", 
            "confidence": 0.0, 
            "word": "נינהו", 
            "gold_class": 0, 
            "predicted": "P"
        }, 
        {
            "lang": 1, 
            "gold_pos": "", 
            "confidence": 0.0, 
            "word": "דתניא", 
            "gold_class": 0, 
            "predicted": "V01"
        }, 
        {
            "lang": 0, 
            "gold_pos": "", 
            "confidence": 1.619348474769435e-07, 
            "word": "תורמין", 
            "gold_class": 0, 
            "predicted": "V02"
        }, 
        {
            "lang": 0, 
            "gold_pos": "", 
            "confidence": 7.2768380915841772e-06, 
            "word": "על", 
            "gold_class": 0, 
            "predicted": "V01"
        }, 
        {
            "lang": 0, 
            "gold_pos": "", 
            "confidence": 0.00010543272927871941, 
            "word": "האבוד", 
            "gold_class": 0, 
            "predicted": "V01"
        }, 
        {
            "lang": 0, 
            "gold_pos": "", 
            "confidence": 3.8564608348556025e-05, 
            "word": "ועל", 
            "gold_class": 0, 
            "predicted": "V01"
        }, 
        {
            "lang": 0, 
            "gold_pos": "", 
            "confidence": 1.0542759886504463e-09, 
            "word": "הגבוי", 
            "gold_class": 0, 
            "predicted": "V01"
        }, 
        {
            "lang": 0, 
            "gold_pos": "", 
            "confidence": 3.8484107539538732e-06, 
            "word": "ועל", 
            "gold_class": 0, 
            "predicted": "a"
        }, 
        {
            "lang": 0, 
            "gold_pos": "", 
            "confidence": 7.3840520946339194e-08, 
            "word": "העתיד", 
            "gold_class": 0, 
            "predicted": "V01"
        }, 
        {
            "lang": 0, 
            "gold_pos": "", 
            "confidence": 0.0011434807173871582, 
            "word": "לגבות", 
            "gold_class": 0, 
            "predicted": "p02"
        }, 
        {
            "lang": 0, 
            "gold_pos": "", 
            "confidence": 1.6280103204478982e-06, 
            "word": "אלא", 
            "gold_class": 0, 
            "predicted": "c"
        }, 
        {
            "lang": 0, 
            "gold_pos": "", 
            "confidence": 3.102091634667951e-09, 
            "word": "אמר", 
            "gold_class": 0, 
            "predicted": "V01"
        }, 
        {
            "lang": 0, 
            "gold_pos": "", 
            "confidence": 1.3175677073695712e-08, 
            "word": "רבי", 
            "gold_class": 0, 
            "predicted": "N05"
        }, 
        {
            "lang": 0, 
            "gold_pos": "", 
            "confidence": 0.0001359094032536991, 
            "word": "אלעזר", 
            "gold_class": 0, 
            "predicted": "V01"
        }, 
        {
            "lang": 0, 
            "gold_pos": "", 
            "confidence": 3.4446463230641086e-06, 
            "word": "שבועה", 
            "gold_class": 0, 
            "predicted": "V01"
        }, 
        {
            "lang": 0, 
            "gold_pos": "", 
            "confidence": 1.3928783491001435e-07, 
            "word": "זו", 
            "gold_class": 0, 
            "predicted": "V01"
        }, 
        {
            "lang": 0, 
            "gold_pos": "", 
            "confidence": 2.9781281798920334e-07, 
            "word": "תקנת", 
            "gold_class": 0, 
            "predicted": "V01"
        }, 
        {
            "lang": 0, 
            "gold_pos": "", 
            "confidence": 3.0701867557927786e-07, 
            "word": "חכמים", 
            "gold_class": 0, 
            "predicted": "V01"
        }, 
        {
            "lang": 0, 
            "gold_pos": "", 
            "confidence": 2.4996342867004718e-05, 
            "word": "היא", 
            "gold_class": 0, 
            "predicted": "P"
        }, 
        {
            "lang": 0, 
            "gold_pos": "", 
            "confidence": 1.0746384592656806e-05, 
            "word": "שלא", 
            "gold_class": 0, 
            "predicted": "V01"
        }, 
        {
            "lang": 1, 
            "gold_pos": "", 
            "confidence": 1.782126924733833e-08, 
            "word": "יהו", 
            "gold_class": 0, 
            "predicted": "V01"
        }, 
        {
            "lang": 0, 
            "gold_pos": "", 
            "confidence": 1.8091481332846736e-05, 
            "word": "בני", 
            "gold_class": 0, 
            "predicted": "N05"
        }, 
        {
            "lang": 0, 
            "gold_pos": "", 
            "confidence": 2.7506809088891544e-05, 
            "word": "אדם", 
            "gold_class": 0, 
            "predicted": "N01"
        }, 
        {
            "lang": 0, 
            "gold_pos": "", 
            "confidence": 6.8947154378634386e-08, 
            "word": "מזלזלים", 
            "gold_class": 0, 
            "predicted": "V02"
        }, 
        {
            "lang": 0, 
            "gold_pos": "", 
            "confidence": 0.00026950545016591921, 
            "word": "בהקדשות", 
            "gold_class": 0, 
            "predicted": "GN"
        }, 
        {
            "lang": 1, 
            "gold_pos": "", 
            "confidence": 1.5389182143635992e-09, 
            "word": "נושא", 
            "gold_class": 0, 
            "predicted": "N02"
        }, 
        {
            "lang": 0, 
            "gold_pos": "", 
            "confidence": 1.1048931336613412e-07, 
            "word": "שכר", 
            "gold_class": 0, 
            "predicted": "V01"
        }, 
        {
            "lang": 0, 
            "gold_pos": "", 
            "confidence": 0.00010854581807272347, 
            "word": "אינו", 
            "gold_class": 0, 
            "predicted": "P"
        }, 
        {
            "lang": 0, 
            "gold_pos": "", 
            "confidence": 8.983172374058444e-07, 
            "word": "משלם", 
            "gold_class": 0, 
            "predicted": "V02"
        }, 
        {
            "lang": 1, 
            "gold_pos": "V01", 
            "confidence": 0.0, 
            "word": "רמי", 
            "gold_class": 1, 
            "predicted": "V01"
        }, 
        {
            "lang": 1, 
            "gold_pos": "p02", 
            "confidence": 0.00012772585000341385, 
            "word": "ליה", 
            "gold_class": 1, 
            "predicted": "p02"
        }, 
        {
            "lang": 1, 
            "gold_pos": "", 
            "confidence": 0.0, 
            "word": "רב", 
            "gold_class": 0, 
            "predicted": "N02"
        }, 
        {
            "lang": 0, 
            "gold_pos": "", 
            "confidence": 9.9513840086905278e-08, 
            "word": "יוסף", 
            "gold_class": 0, 
            "predicted": "PN"
        }, 
        {
            "lang": 1, 
            "gold_pos": "", 
            "confidence": 2.8492202348075841e-08, 
            "word": "בר", 
            "gold_class": 0, 
            "predicted": "N01"
        }, 
        {
            "lang": 1, 
            "gold_pos": "", 
            "confidence": 2.9352281537059039e-05, 
            "word": "חמא", 
            "gold_class": 0, 
            "predicted": "V01"
        }, 
        {
            "lang": 1, 
            "gold_pos": "", 
            "confidence": 0.0, 
            "word": "לרבה", 
            "gold_class": 0, 
            "predicted": "PN"
        }, 
        {
            "lang": 1, 
            "gold_pos": "", 
            "confidence": 0.0, 
            "word": "תנן", 
            "gold_class": 0, 
            "predicted": "V01"
        }, 
        {
            "lang": 1, 
            "gold_pos": "", 
            "confidence": 1.1304423568808833e-07, 
            "word": "נושא", 
            "gold_class": 0, 
            "predicted": "N02"
        }, 
        {
            "lang": 0, 
            "gold_pos": "", 
            "confidence": 4.5673724876775598e-07, 
            "word": "שכר", 
            "gold_class": 0, 
            "predicted": "V01"
        }, 
        {
            "lang": 0, 
            "gold_pos": "", 
            "confidence": 2.2891209748091327e-05, 
            "word": "אינו", 
            "gold_class": 0, 
            "predicted": "P"
        }, 
        {
            "lang": 0, 
            "gold_pos": "", 
            "confidence": 5.3019179492011284e-07, 
            "word": "משלם", 
            "gold_class": 0, 
            "predicted": "V02"
        }, 
        {
            "lang": 1, 
            "gold_pos": "V01", 
            "confidence": 0.0, 
            "word": "ורמינהו", 
            "gold_class": 1, 
            "predicted": "V01"
        }, 
        {
            "lang": 0, 
            "gold_pos": "", 
            "confidence": 1.8543036175430387e-05, 
            "word": "השוכר", 
            "gold_class": 0, 
            "predicted": "V01"
        }, 
        {
            "lang": 0, 
            "gold_pos": "", 
            "confidence": 3.5992331043037818e-07, 
            "word": "את", 
            "gold_class": 0, 
            "predicted": "V01"
        }, 
        {
            "lang": 0, 
            "gold_pos": "", 
            "confidence": 7.5111105435281537e-08, 
            "word": "הפועל", 
            "gold_class": 0, 
            "predicted": "V01"
        }, 
        {
            "lang": 0, 
            "gold_pos": "", 
            "confidence": 0.00087556035444296375, 
            "word": "לשמור", 
            "gold_class": 0, 
            "predicted": "n01"
        }, 
        {
            "lang": 0, 
            "gold_pos": "", 
            "confidence": 2.0435746331674741e-07, 
            "word": "את", 
            "gold_class": 0, 
            "predicted": "V01"
        }, 
        {
            "lang": 0, 
            "gold_pos": "", 
            "confidence": 2.2857632306726131e-09, 
            "word": "הפרה", 
            "gold_class": 0, 
            "predicted": "V01"
        }, 
        {
            "lang": 0, 
            "gold_pos": "", 
            "confidence": 6.8466837117781986e-05, 
            "word": "לשמור", 
            "gold_class": 0, 
            "predicted": "V02"
        }, 
        {
            "lang": 0, 
            "gold_pos": "", 
            "confidence": 4.9402887374004078e-06, 
            "word": "את", 
            "gold_class": 0, 
            "predicted": "V01"
        }, 
        {
            "lang": 0, 
            "gold_pos": "", 
            "confidence": 2.2138874154848898e-10, 
            "word": "התינוק", 
            "gold_class": 0, 
            "predicted": "V01"
        }, 
        {
            "lang": 0, 
            "gold_pos": "", 
            "confidence": 0.00016979779523918046, 
            "word": "לשמור", 
            "gold_class": 0, 
            "predicted": "n01"
        }, 
        {
            "lang": 0, 
            "gold_pos": "", 
            "confidence": 2.7594109102032034e-08, 
            "word": "את", 
            "gold_class": 0, 
            "predicted": "V01"
        }, 
        {
            "lang": 0, 
            "gold_pos": "", 
            "confidence": 1.961957637976683e-07, 
            "word": "הזרעים", 
            "gold_class": 0, 
            "predicted": "N02"
        }, 
        {
            "lang": 0, 
            "gold_pos": "", 
            "confidence": 2.0782526023244597e-06, 
            "word": "אין", 
            "gold_class": 0, 
            "predicted": "P"
        }, 
        {
            "lang": 0, 
            "gold_pos": "", 
            "confidence": 6.4080349775730572e-09, 
            "word": "נותנים", 
            "gold_class": 0, 
            "predicted": "V01"
        }, 
        {
            "lang": 0, 
            "gold_pos": "", 
            "confidence": 0.0020834648837399217, 
            "word": "לו", 
            "gold_class": 0, 
            "predicted": "N02"
        }, 
        {
            "lang": 0, 
            "gold_pos": "", 
            "confidence": 4.604810048284015e-07, 
            "word": "שכר", 
            "gold_class": 0, 
            "predicted": "V01"
        }, 
        {
            "lang": 0, 
            "gold_pos": "", 
            "confidence": 6.7202779596986994e-05, 
            "word": "שבת", 
            "gold_class": 0, 
            "predicted": "V02"
        }, 
        {
            "lang": 0, 
            "gold_pos": "", 
            "confidence": 0.00081871388678482363, 
            "word": "לפיכך", 
            "gold_class": 0, 
            "predicted": "N01"
        }, 
        {
            "lang": 0, 
            "gold_pos": "", 
            "confidence": 9.1710248046380596e-05, 
            "word": "אין", 
            "gold_class": 0, 
            "predicted": "P"
        }, 
        {
            "lang": 0, 
            "gold_pos": "", 
            "confidence": 5.4750400823721782e-06, 
            "word": "אחריות", 
            "gold_class": 0, 
            "predicted": "P"
        }, 
        {
            "lang": 0, 
            "gold_pos": "", 
            "confidence": 1.1289885045115349e-05, 
            "word": "שבת", 
            "gold_class": 0, 
            "predicted": "V01"
        }, 
        {
            "lang": 0, 
            "gold_pos": "", 
            "confidence": 9.8643867391208051e-05, 
            "word": "עליו", 
            "gold_class": 0, 
            "predicted": "V02"
        }, 
        {
            "lang": 0, 
            "gold_pos": "", 
            "confidence": 6.0946190977944299e-06, 
            "word": "היה", 
            "gold_class": 0, 
            "predicted": "P"
        }, 
        {
            "lang": 1, 
            "gold_pos": "", 
            "confidence": 4.1656923872330596e-06, 
            "word": "שכיר", 
            "gold_class": 0, 
            "predicted": "A01"
        }, 
        {
            "lang": 0, 
            "gold_pos": "", 
            "confidence": 0.00066225190737182697, 
            "word": "שבת", 
            "gold_class": 0, 
            "predicted": "V01"
        }, 
        {
            "lang": 1, 
            "gold_pos": "", 
            "confidence": 1.7776094445526327e-08, 
            "word": "שכיר", 
            "gold_class": 0, 
            "predicted": "A01"
        }, 
        {
            "lang": 0, 
            "gold_pos": "", 
            "confidence": 1.8607615131775164e-05, 
            "word": "חדש", 
            "gold_class": 0, 
            "predicted": "V01"
        }, 
        {
            "lang": 1, 
            "gold_pos": "", 
            "confidence": 1.8552741509190192e-07, 
            "word": "שכיר", 
            "gold_class": 0, 
            "predicted": "A01"
        }, 
        {
            "lang": 0, 
            "gold_pos": "", 
            "confidence": 3.6352227343711374e-07, 
            "word": "שנה", 
            "gold_class": 0, 
            "predicted": "V01"
        }, 
        {
            "lang": 1, 
            "gold_pos": "", 
            "confidence": 1.985618050122228e-07, 
            "word": "שכיר", 
            "gold_class": 0, 
            "predicted": "A01"
        }, 
        {
            "lang": 0, 
            "gold_pos": "", 
            "confidence": 1.2702719571453773e-08, 
            "word": "שבוע", 
            "gold_class": 0, 
            "predicted": "V02"
        }, 
        {
            "lang": 0, 
            "gold_pos": "", 
            "confidence": 2.4019534966702533e-06, 
            "word": "נותנין", 
            "gold_class": 0, 
            "predicted": "V01"
        }, 
        {
            "lang": 0, 
            "gold_pos": "", 
            "confidence": 0.00013534116384871701, 
            "word": "לו", 
            "gold_class": 0, 
            "predicted": "N02"
        }, 
        {
            "lang": 0, 
            "gold_pos": "", 
            "confidence": 1.7602568758581899e-07, 
            "word": "שכר", 
            "gold_class": 0, 
            "predicted": "V01"
        }, 
        {
            "lang": 0, 
            "gold_pos": "", 
            "confidence": 4.3636138732573911e-05, 
            "word": "שבת", 
            "gold_class": 0, 
            "predicted": "V01"
        }, 
        {
            "lang": 0, 
            "gold_pos": "", 
            "confidence": 0.00017795477795993849, 
            "word": "לפיכך", 
            "gold_class": 0, 
            "predicted": "p02"
        }, 
        {
            "lang": 0, 
            "gold_pos": "", 
            "confidence": 0.00073649790582167962, 
            "word": "אחריות", 
            "gold_class": 0, 
            "predicted": "P"
        }, 
        {
            "lang": 0, 
            "gold_pos": "", 
            "confidence": 3.9235155322105878e-05, 
            "word": "שבת", 
            "gold_class": 0, 
            "predicted": "V01"
        }, 
        {
            "lang": 0, 
            "gold_pos": "", 
            "confidence": 1.1324967893861307e-05, 
            "word": "עליו", 
            "gold_class": 0, 
            "predicted": "V01"
        }, 
        {
            "lang": 1, 
            "gold_pos": "P", 
            "confidence": 0.0, 
            "word": "מאי", 
            "gold_class": 1, 
            "predicted": "P"
        }, 
        {
            "lang": 0, 
            "gold_pos": "a", 
            "confidence": 1.524075551198865e-10, 
            "word": "לאו", 
            "gold_class": 0, 
            "predicted": "a"
        }, 
        {
            "lang": 0, 
            "gold_pos": "V02", 
            "confidence": 1.2460755975961125e-07, 
            "word": "לשלם", 
            "gold_class": 0, 
            "predicted": "V02"
        }, 
        {
            "lang": 0, 
            "gold_pos": "a", 
            "confidence": 9.1134171336925896e-08, 
            "word": "לא", 
            "gold_class": 0, 
            "predicted": "a"
        }, 
        {
            "lang": 0, 
            "gold_pos": "", 
            "confidence": 6.3427020452825104e-05, 
            "word": "להפסיד", 
            "gold_class": 0, 
            "predicted": "V01"
        }, 
        {
            "lang": 0, 
            "gold_pos": "", 
            "confidence": 2.1958162571051216e-08, 
            "word": "שכרו", 
            "gold_class": 0, 
            "predicted": "V01"
        }, 
        {
            "lang": 1, 
            "gold_pos": "c", 
            "confidence": 0.0, 
            "word": "אי", 
            "gold_class": 1, 
            "predicted": "c"
        }, 
        {
            "lang": 1, 
            "gold_pos": "a", 
            "confidence": 0.0, 
            "word": "הכי", 
            "gold_class": 1, 
            "predicted": "a"
        }, 
        {
            "lang": 1, 
            "gold_pos": "N02", 
            "confidence": 0.0, 
            "word": "רישא", 
            "gold_class": 1, 
            "predicted": "N02"
        }, 
        {
            "lang": 1, 
            "gold_pos": "V01", 
            "confidence": 0.0, 
            "word": "דקתני", 
            "gold_class": 1, 
            "predicted": "V01"
        }, 
        {
            "lang": 0, 
            "gold_pos": "", 
            "confidence": 2.1249499032639813e-08, 
            "word": "אין", 
            "gold_class": 0, 
            "predicted": "P"
        }, 
        {
            "lang": 0, 
            "gold_pos": "", 
            "confidence": 1.9376982690916834e-07, 
            "word": "אחריות", 
            "gold_class": 0, 
            "predicted": "P"
        }, 
        {
            "lang": 0, 
            "gold_pos": "", 
            "confidence": 1.5103468363819456e-07, 
            "word": "שבת", 
            "gold_class": 0, 
            "predicted": "V01"
        }, 
        {
            "lang": 0, 
            "gold_pos": "", 
            "confidence": 4.8760080874722867e-06, 
            "word": "עליו", 
            "gold_class": 0, 
            "predicted": "V02"
        }, 
        {
            "lang": 1, 
            "gold_pos": "", 
            "confidence": 0.0, 
            "word": "הכי", 
            "gold_class": 0, 
            "predicted": "a"
        }, 
        {
            "lang": 1, 
            "gold_pos": "", 
            "confidence": 0.0, 
            "word": "נמי", 
            "gold_class": 0, 
            "predicted": "a"
        }, 
        {
            "lang": 1, 
            "gold_pos": "", 
            "confidence": 5.3334992085955545e-07, 
            "word": "דלהפסיד", 
            "gold_class": 0, 
            "predicted": "a"
        }, 
        {
            "lang": 0, 
            "gold_pos": "", 
            "confidence": 2.4792433596102104e-07, 
            "word": "שכרו", 
            "gold_class": 0, 
            "predicted": "V02"
        }, 
        {
            "lang": 0, 
            "gold_pos": "", 
            "confidence": 1.2350417604775444e-05, 
            "word": "ומי", 
            "gold_class": 0, 
            "predicted": "V01"
        }, 
        {
            "lang": 1, 
            "gold_pos": "", 
            "confidence": 0.0, 
            "word": "אית", 
            "gold_class": 0, 
            "predicted": "a"
        }, 
        {
            "lang": 1, 
            "gold_pos": "", 
            "confidence": 1.7536879742177433e-07, 
            "word": "ליה", 
            "gold_class": 0, 
            "predicted": "p02"
        }, 
        {
            "lang": 0, 
            "gold_pos": "", 
            "confidence": 2.9686615389635955e-07, 
            "word": "שכר", 
            "gold_class": 0, 
            "predicted": "V01"
        }, 
        {
            "lang": 0, 
            "gold_pos": "", 
            "confidence": 3.2018710819463863e-06, 
            "word": "שבת", 
            "gold_class": 0, 
            "predicted": "V01"
        }, 
        {
            "lang": 1, 
            "gold_pos": "", 
            "confidence": 0.0, 
            "word": "והא", 
            "gold_class": 0, 
            "predicted": "I"
        }, 
        {
            "lang": 1, 
            "gold_pos": "V01", 
            "confidence": 0.0, 
            "word": "קתני", 
            "gold_class": 1, 
            "predicted": "V01"
        }, 
        {
            "lang": 0, 
            "gold_pos": "", 
            "confidence": 8.838212192846521e-07, 
            "word": "אין", 
            "gold_class": 0, 
            "predicted": "P"
        }, 
        {
            "lang": 0, 
            "gold_pos": "", 
            "confidence": 2.3561751816612691e-09, 
            "word": "נותנין", 
            "gold_class": 0, 
            "predicted": "V01"
        }, 
        {
            "lang": 0, 
            "gold_pos": "", 
            "confidence": 1.3689937465458173e-05, 
            "word": "לו", 
            "gold_class": 0, 
            "predicted": "N02"
        }, 
        {
            "lang": 0, 
            "gold_pos": "", 
            "confidence": 2.451724178809698e-07, 
            "word": "שכר", 
            "gold_class": 0, 
            "predicted": "V01"
        }, 
        {
            "lang": 0, 
            "gold_pos": "", 
            "confidence": 3.5489974667191931e-05, 
            "word": "שבת", 
            "gold_class": 0, 
            "predicted": "n01"
        }, 
        {
            "lang": 1, 
            "gold_pos": "V01", 
            "confidence": 0.0, 
            "word": "אשתיק", 
            "gold_class": 1, 
            "predicted": "V01"
        }, 
        {
            "lang": 0, 
            "gold_pos": "", 
            "confidence": 9.9914981656487066e-11, 
            "word": "אמר", 
            "gold_class": 0, 
            "predicted": "V01"
        }, 
        {
            "lang": 1, 
            "gold_pos": "p02", 
            "confidence": 7.4864518066524408e-06, 
            "word": "ליה", 
            "gold_class": 1, 
            "predicted": "p02"
        }, 
        {
            "lang": 1, 
            "gold_pos": "c", 
            "confidence": 0.0, 
            "word": "מידי", 
            "gold_class": 1, 
            "predicted": "c"
        }, 
        {
            "lang": 1, 
            "gold_pos": "V01", 
            "confidence": 0.0, 
            "word": "שמיע", 
            "gold_class": 1, 
            "predicted": "V01"
        }, 
        {
            "lang": 0, 
            "gold_pos": "p02", 
            "confidence": 2.7645311485904444e-07, 
            "word": "לך", 
            "gold_class": 0, 
            "predicted": "p02"
        }, 
        {
            "lang": 1, 
            "gold_pos": "P", 
            "confidence": 0.0, 
            "word": "בהא", 
            "gold_class": 1, 
            "predicted": "P"
        }, 
        {
            "lang": 0, 
            "gold_pos": "", 
            "confidence": 1.2553346841406277e-10, 
            "word": "אמר", 
            "gold_class": 0, 
            "predicted": "V01"
        }, 
        {
            "lang": 1, 
            "gold_pos": "", 
            "confidence": 5.633924658130282e-06, 
            "word": "ליה", 
            "gold_class": 0, 
            "predicted": "p02"
        }, 
        {
            "lang": 1, 
            "gold_pos": "", 
            "confidence": 0.0, 
            "word": "הכי", 
            "gold_class": 0, 
            "predicted": "a"
        }, 
        {
            "lang": 0, 
            "gold_pos": "", 
            "confidence": 5.0128243544562284e-11, 
            "word": "אמר", 
            "gold_class": 0, 
            "predicted": "V01"
        }, 
        {
            "lang": 1, 
            "gold_pos": "", 
            "confidence": 0.0, 
            "word": "רב", 
            "gold_class": 0, 
            "predicted": "N02"
        }, 
        {
            "lang": 0, 
            "gold_pos": "", 
            "confidence": 9.9988228951862077e-08, 
            "word": "ששת", 
            "gold_class": 0, 
            "predicted": "V01"
        }, 
        {
            "lang": 0, 
            "gold_pos": "", 
            "confidence": 4.2177032257519413e-09, 
            "word": "בשקנו", 
            "gold_class": 0, 
            "predicted": "V01"
        }, 
        {
            "lang": 0, 
            "gold_pos": "", 
            "confidence": 0.00034248138412571789, 
            "word": "מידו", 
            "gold_class": 0, 
            "predicted": "P"
        }, 
        {
            "lang": 0, 
            "gold_pos": "", 
            "confidence": 2.9028474803352262e-05, 
            "word": "וכן", 
            "gold_class": 0, 
            "predicted": "c"
        }, 
        {
            "lang": 0, 
            "gold_pos": "", 
            "confidence": 1.2706478720856641e-09, 
            "word": "אמר", 
            "gold_class": 0, 
            "predicted": "V01"
        }, 
        {
            "lang": 0, 
            "gold_pos": "", 
            "confidence": 2.6403512568057193e-06, 
            "word": "רבי", 
            "gold_class": 0, 
            "predicted": "N02"
        }, 
        {
            "lang": 0, 
            "gold_pos": "", 
            "confidence": 5.0463785381857278e-08, 
            "word": "יוחנן", 
            "gold_class": 0, 
            "predicted": "N05"
        }, 
        {
            "lang": 0, 
            "gold_pos": "", 
            "confidence": 1.011854539989449e-06, 
            "word": "בשקנו", 
            "gold_class": 0, 
            "predicted": "V02"
        }, 
        {
            "lang": 0, 
            "gold_pos": "", 
            "confidence": 0.001087293271543928, 
            "word": "מידו", 
            "gold_class": 0, 
            "predicted": "c"
        }, 
        {
            "lang": 0, 
            "gold_pos": "", 
            "confidence": 1.934585573120644e-07, 
            "word": "רבי", 
            "gold_class": 0, 
            "predicted": "N02"
        }, 
        {
            "lang": 0, 
            "gold_pos": "", 
            "confidence": 3.5911704278014383e-07, 
            "word": "שמעון", 
            "gold_class": 0, 
            "predicted": "V01"
        }, 
        {
            "lang": 0, 
            "gold_pos": "", 
            "confidence": 4.0802244328980659e-06, 
            "word": "אומר", 
            "gold_class": 0, 
            "predicted": "V03"
        }, 
        {
            "lang": 0, 
            "gold_pos": "", 
            "confidence": 2.7762257276245378e-06, 
            "word": "קדשים", 
            "gold_class": 0, 
            "predicted": "V02"
        }, 
        {
            "lang": 1, 
            "gold_pos": "", 
            "confidence": 2.4680616971049762e-08, 
            "word": "שחייב", 
            "gold_class": 0, 
            "predicted": "V05"
        }, 
        {
            "lang": 0, 
            "gold_pos": "", 
            "confidence": 0.018565060290630007, 
            "word": "באחריותן", 
            "gold_class": 0, 
            "predicted": "p02"
        }, 
        {
            "lang": 0, 
            "gold_pos": "", 
            "confidence": 2.8184861157362775e-07, 
            "word": "יש", 
            "gold_class": 0, 
            "predicted": "V01"
        }, 
        {
            "lang": 0, 
            "gold_pos": "", 
            "confidence": 9.0856311250873652e-05, 
            "word": "להן", 
            "gold_class": 0, 
            "predicted": "p02"
        }, 
        {
            "lang": 1, 
            "gold_pos": "", 
            "confidence": 8.5618429406943318e-06, 
            "word": "אונאה", 
            "gold_class": 0, 
            "predicted": "N02"
        }, 
        {
            "lang": 0, 
            "gold_pos": "", 
            "confidence": 0.00014586142982905964, 
            "word": "ושאינו", 
            "gold_class": 0, 
            "predicted": "c"
        }, 
        {
            "lang": 0, 
            "gold_pos": "", 
            "confidence": 3.1738004872816336e-08, 
            "word": "חייב", 
            "gold_class": 0, 
            "predicted": "V02"
        }, 
        {
            "lang": 0, 
            "gold_pos": "", 
            "confidence": 0.00091142143764442974, 
            "word": "באחריותן", 
            "gold_class": 0, 
            "predicted": "p02"
        }, 
        {
            "lang": 0, 
            "gold_pos": "", 
            "confidence": 3.1221085335117357e-09, 
            "word": "אין", 
            "gold_class": 0, 
            "predicted": "P"
        }, 
        {
            "lang": 0, 
            "gold_pos": "", 
            "confidence": 5.9717917299122766e-06, 
            "word": "להן", 
            "gold_class": 0, 
            "predicted": "P"
        }, 
        {
            "lang": 1, 
            "gold_pos": "", 
            "confidence": 0.0027238961512986515, 
            "word": "אונאה", 
            "gold_class": 0, 
            "predicted": "N02"
        }, 
        {
            "lang": 1, 
            "gold_pos": "V01", 
            "confidence": 0.0, 
            "word": "תני", 
            "gold_class": 1, 
            "predicted": "V01"
        }, 
        {
            "lang": 1, 
            "gold_pos": "N02", 
            "confidence": 0.0, 
            "word": "תנא", 
            "gold_class": 1, 
            "predicted": "N02"
        }, 
        {
            "lang": 1, 
            "gold_pos": "p02", 
            "confidence": 0.0, 
            "word": "קמיה", 
            "gold_class": 1, 
            "predicted": "p02"
        }, 
        {
            "lang": 1, 
            "gold_pos": "", 
            "confidence": 0.0, 
            "word": "דרבי", 
            "gold_class": 0, 
            "predicted": "PN"
        }, 
        {
            "lang": 0, 
            "gold_pos": "", 
            "confidence": 5.1859537698114052e-09, 
            "word": "יצחק", 
            "gold_class": 0, 
            "predicted": "V01"
        }, 
        {
            "lang": 1, 
            "gold_pos": "N01", 
            "confidence": 7.1347464697230481e-09, 
            "word": "בר", 
            "gold_class": 1, 
            "predicted": "N01"
        }, 
        {
            "lang": 0, 
            "gold_pos": "", 
            "confidence": 5.366014270428302e-05, 
            "word": "אבא", 
            "gold_class": 0, 
            "predicted": "N02"
        }, 
        {
            "lang": 0, 
            "gold_pos": "", 
            "confidence": 8.4112044095676479e-06, 
            "word": "קדשים", 
            "gold_class": 0, 
            "predicted": "V02"
        }, 
        {
            "lang": 1, 
            "gold_pos": "", 
            "confidence": 1.6829551173948508e-07, 
            "word": "שחייב", 
            "gold_class": 0, 
            "predicted": "V05"
        }, 
        {
            "lang": 0, 
            "gold_pos": "", 
            "confidence": 0.0058857842783876452, 
            "word": "באחריותן", 
            "gold_class": 0, 
            "predicted": "p02"
        }, 
        {
            "lang": 0, 
            "gold_pos": "", 
            "confidence": 5.0933942756564423e-09, 
            "word": "חייב", 
            "gold_class": 0, 
            "predicted": "V02"
        }, 
        {
            "lang": 0, 
            "gold_pos": "", 
            "confidence": 1.6133462882708247e-07, 
            "word": "שאני", 
            "gold_class": 0, 
            "predicted": "N05"
        }, 
        {
            "lang": 0, 
            "gold_pos": "", 
            "confidence": 2.4117491575516751e-06, 
            "word": "קורא", 
            "gold_class": 0, 
            "predicted": "N02"
        }, 
        {
            "lang": 0, 
            "gold_pos": "", 
            "confidence": 0.00011878574247542336, 
            "word": "בהן", 
            "gold_class": 0, 
            "predicted": "p02"
        }, 
        {
            "lang": 0, 
            "gold_pos": "", 
            "confidence": 4.1813647948762103e-05, 
            "word": "בה׳", 
            "gold_class": 0, 
            "predicted": "P"
        }, 
        {
            "lang": 0, 
            "gold_pos": "", 
            "confidence": 5.2066038430764821e-07, 
            "word": "וכחש", 
            "gold_class": 0, 
            "predicted": "V01"
        }, 
        {
            "lang": 0, 
            "gold_pos": "", 
            "confidence": 1.2341500786440146e-05, 
            "word": "ושאינו", 
            "gold_class": 0, 
            "predicted": "V01"
        }, 
        {
            "lang": 0, 
            "gold_pos": "", 
            "confidence": 7.5484270163465014e-08, 
            "word": "חייב", 
            "gold_class": 0, 
            "predicted": "V05"
        }, 
        {
            "lang": 0, 
            "gold_pos": "", 
            "confidence": 0.01549050261471518, 
            "word": "באחריותן", 
            "gold_class": 0, 
            "predicted": "p02"
        }, 
        {
            "lang": 0, 
            "gold_pos": "", 
            "confidence": 1.0732902787111266e-07, 
            "word": "פטור", 
            "gold_class": 0, 
            "predicted": "V01"
        }, 
        {
            "lang": 0, 
            "gold_pos": "", 
            "confidence": 1.1068295254966691e-07, 
            "word": "שאני", 
            "gold_class": 0, 
            "predicted": "N05"
        }, 
        {
            "lang": 0, 
            "gold_pos": "", 
            "confidence": 1.8409389775847812e-06, 
            "word": "קורא", 
            "gold_class": 0, 
            "predicted": "N02"
        }, 
        {
            "lang": 0, 
            "gold_pos": "", 
            "confidence": 8.6976880398162091e-07, 
            "word": "בהן", 
            "gold_class": 0, 
            "predicted": "p02"
        }, 
        {
            "lang": 0, 
            "gold_pos": "", 
            "confidence": 3.0796322006941708e-05, 
            "word": "בעמיתו", 
            "gold_class": 0, 
            "predicted": "N02"
        }, 
        {
            "lang": 0, 
            "gold_pos": "", 
            "confidence": 1.0522334144244765e-06, 
            "word": "וכחש", 
            "gold_class": 0, 
            "predicted": "V01"
        }, 
        {
            "lang": 0, 
            "gold_pos": "", 
            "confidence": 4.1887163704906939e-10, 
            "word": "אמר", 
            "gold_class": 0, 
            "predicted": "V01"
        }, 
        {
            "lang": 1, 
            "gold_pos": "p02", 
            "confidence": 1.6427328985824943e-06, 
            "word": "ליה", 
            "gold_class": 1, 
            "predicted": "p02"
        }, 
        {
            "lang": 0, 
            "gold_pos": "a", 
            "confidence": 1.1186855160268175e-07, 
            "word": "כלפי", 
            "gold_class": 0, 
            "predicted": "N05"
        }, 
        {
            "lang": 1, 
            "gold_pos": "a", 
            "confidence": 0.0, 
            "word": "לייא", 
            "gold_class": 1, 
            "predicted": "a"
        }
    ]
}